{
  "correlation_id": "node-github-009",
  "node_type": null,
  "skill_name": "code-convert",
  "created_at": "2026-01-06T08:30:21.767558",
  "generated_code": {
    "github.py": "#!/usr/bin/env python3\n\"\"\"\nGithub Node\n\nConverted from TypeScript by agent-skills/code-convert\nCorrelation ID: node-github-009\nGenerated: 2026-01-06T08:30:21.759004\n\nSYNC-CELERY SAFE: All methods are synchronous with timeouts.\n\"\"\"\n\nfrom __future__ import annotations\n\nimport logging\nfrom typing import Any, Dict, List\n\nimport requests\n\nfrom .base import BaseNode, NodeParameterType, NodeExecutionData\n\nlogger = logging.getLogger(__name__)\n\n\nclass GithubNode(BaseNode):\n    \"\"\"\n    Node node.\n    \n    \n    \"\"\"\n\n    type = \"github\"\n    version = 1\n    \n    description = {\n        \"displayName\": \"Node\",\n        \"name\": \"github\",\n        \"icon\": \"file:github.svg\",\n        \"group\": ['output'],\n        \"description\": \"\",\n        \"inputs\": [{\"name\": \"main\", \"type\": \"main\", \"required\": True}],\n        \"outputs\": [{\"name\": \"main\", \"type\": \"main\", \"required\": True}],\n    }\n    \n    properties = {\n        \"parameters\": [\n            {\"name\": \"operation\", \"type\": NodeParameterType.OPTIONS, \"display_name\": \"Operation\", \"options\": [\n                {\"name\": \"Get Repositories\", \"value\": \"getRepositories\", \"description\": \"Returns all repositories of an organization\"},\n                {\"name\": \"checkExists\", \"value\": \"checkExists\", \"description\": \"Operation: checkExists\"},\n                {\"name\": \"create\", \"value\": \"create\", \"description\": \"Operation: create\"},\n                {\"name\": \"webhook\", \"value\": \"webhook\", \"description\": \"Operation: webhook\"},\n                {\"name\": \"getUsers\", \"value\": \"getUsers\", \"description\": \"Operation: getUsers\"},\n                {\"name\": \"getRepositories\", \"value\": \"getRepositories\", \"description\": \"Operation: getRepositories\"},\n                {\"name\": \"getWorkflows\", \"value\": \"getWorkflows\", \"description\": \"Operation: getWorkflows\"},\n                {\"name\": \"getRefs\", \"value\": \"getRefs\", \"description\": \"Operation: getRefs\"}\n            ], \"default\": \"getRepositories\", \"description\": \"Operation to perform\"},\n            {\"name\": \"authentication\", \"type\": NodeParameterType.OPTIONS, \"display_name\": \"Authentication\", \"options\": [\n                {\"name\": \"Access Token\", \"value\": \"accessToken\"},\n                {\"name\": \"OAuth2\", \"value\": \"oAuth2\"}\n            ], \"default\": \"accessToken\"},\n            {\"name\": \"webhookNotice\", \"type\": NodeParameterType.STRING, \"display_name\": \"Your execution will pause until a webhook is called. This URL will be generated at runtime and passed to your Github workflow as a resumeUrl input.\", \"default\": \"\", \"display_options\": {'show': {'operation': ['dispatchAndWait'], 'resource': ['workflow']}}},\n            {\"name\": \"owner\", \"type\": NodeParameterType.STRING, \"display_name\": \"Repository Owner\", \"default\": \"\", \"required\": True},\n            {\"name\": \"repository\", \"type\": NodeParameterType.STRING, \"display_name\": \"Repository Name\", \"default\": \"\", \"required\": True},\n            {\"name\": \"workflowId\", \"type\": NodeParameterType.STRING, \"display_name\": \"Workflow\", \"default\": \"\", \"required\": True, \"description\": \"The workflow to dispatch\", \"display_options\": {'show': {'operation': ['disable', 'dispatch', 'dispatchAndWait', 'get', 'getUsage', 'enable'], 'resource': ['workflow']}}},\n            {\"name\": \"ref\", \"type\": NodeParameterType.STRING, \"display_name\": \"Ref\", \"default\": \"main\", \"required\": True, \"description\": \"The git reference for the workflow dispatch (branch or tag name)\", \"display_options\": {'show': {'operation': ['dispatch', 'dispatchAndWait'], 'resource': ['workflow']}}},\n            {\"name\": \"inputs\", \"type\": NodeParameterType.JSON, \"display_name\": \"Inputs\", \"default\": \"{}\", \"description\": \"JSON object with input parameters for the workflow\", \"display_options\": {'show': {'operation': ['dispatch', 'dispatchAndWait'], 'resource': ['workflow']}}},\n            {\"name\": \"filePath\", \"type\": NodeParameterType.STRING, \"display_name\": \"File Path\", \"default\": \"\", \"required\": True, \"description\": \"The file path of the file. Has to contain the full path.\", \"display_options\": {'show': {'resource': ['file']}}},\n            {\"name\": \"binaryData\", \"type\": NodeParameterType.BOOLEAN, \"display_name\": \"Binary File\", \"default\": False, \"required\": True, \"description\": \"Whether the data to upload should be taken from binary field\", \"display_options\": {'show': {'operation': ['create', 'edit'], 'resource': ['file']}}},\n            {\"name\": \"fileContent\", \"type\": NodeParameterType.STRING, \"display_name\": \"File Content\", \"default\": \"\", \"required\": True, \"description\": \"The text content of the file\", \"display_options\": {'show': {'operation': ['create', 'edit'], 'resource': ['file']}}},\n            {\"name\": \"binaryPropertyName\", \"type\": NodeParameterType.STRING, \"display_name\": \"Input Binary Field\", \"default\": \"data\", \"required\": True, \"display_options\": {'show': {'operation': ['create', 'edit'], 'resource': ['file']}}},\n            {\"name\": \"commitMessage\", \"type\": NodeParameterType.STRING, \"display_name\": \"Commit Message\", \"default\": \"\", \"required\": True, \"display_options\": {'show': {'operation': ['create', 'delete', 'edit'], 'resource': ['file']}}},\n            {\"name\": \"additionalParameters\", \"type\": NodeParameterType.COLLECTION, \"display_name\": \"Additional Parameters\", \"default\": \"\", \"description\": \"Additional fields to add\", \"display_options\": {'show': {'operation': ['create', 'delete', 'edit'], 'resource': ['file']}}},\n            {\"name\": \"asBinaryProperty\", \"type\": NodeParameterType.BOOLEAN, \"display_name\": \"As Binary Property\", \"default\": True, \"description\": \"Whether to set the data of the file as binary property instead of returning the raw API response\", \"display_options\": {'show': {'operation': ['get'], 'resource': ['file']}}},\n            {\"name\": \"title\", \"type\": NodeParameterType.STRING, \"display_name\": \"Title\", \"default\": \"\", \"required\": True, \"description\": \"The title of the issue\", \"display_options\": {'show': {'operation': ['create'], 'resource': ['issue']}}},\n            {\"name\": \"body\", \"type\": NodeParameterType.STRING, \"display_name\": \"Body\", \"default\": \"\", \"description\": \"The body of the issue\", \"display_options\": {'show': {'operation': ['create'], 'resource': ['issue']}}},\n            {\"name\": \"labels\", \"type\": NodeParameterType.COLLECTION, \"display_name\": \"Labels\", \"default\": \"\", \"description\": \"Label to add to issue\", \"display_options\": {'show': {'operation': ['create'], 'resource': ['issue']}}},\n            {\"name\": \"assignees\", \"type\": NodeParameterType.COLLECTION, \"display_name\": \"Assignees\", \"default\": \"\", \"description\": \"User to assign issue too\", \"display_options\": {'show': {'operation': ['create'], 'resource': ['issue']}}},\n            {\"name\": \"issueNumber\", \"type\": NodeParameterType.NUMBER, \"display_name\": \"Issue Number\", \"default\": 0, \"required\": True, \"description\": \"The number of the issue on which to create the comment on\", \"display_options\": {'show': {'operation': ['createComment'], 'resource': ['issue']}}},\n            {\"name\": \"editFields\", \"type\": NodeParameterType.COLLECTION, \"display_name\": \"Edit Fields\", \"default\": \"\", \"description\": \"User to assign issue to\", \"display_options\": {'show': {'operation': ['edit'], 'resource': ['issue']}}},\n            {\"name\": \"lockReason\", \"type\": NodeParameterType.OPTIONS, \"display_name\": \"Lock Reason\", \"options\": [\n                {\"name\": \"Off-Topic\", \"value\": \"off-topic\"},\n                {\"name\": \"Too Heated\", \"value\": \"too heated\"},\n                {\"name\": \"Resolved\", \"value\": \"resolved\"},\n                {\"name\": \"Spam\", \"value\": \"spam\"}\n            ], \"default\": \"resolved\", \"description\": \"The issue is Off-Topic\", \"display_options\": {'show': {'operation': ['lock'], 'resource': ['issue']}}},\n            {\"name\": \"releaseTag\", \"type\": NodeParameterType.STRING, \"display_name\": \"Tag\", \"default\": \"\", \"required\": True, \"description\": \"The tag of the release\", \"display_options\": {'show': {'operation': ['create'], 'resource': ['release']}}},\n            {\"name\": \"additionalFields\", \"type\": NodeParameterType.COLLECTION, \"display_name\": \"Additional Fields\", \"default\": \"\", \"description\": \"The name of the issue\", \"display_options\": {'show': {'operation': ['create'], 'resource': ['release']}}},\n            {\"name\": \"release_id\", \"type\": NodeParameterType.STRING, \"display_name\": \"Release ID\", \"default\": \"\", \"required\": True, \"display_options\": {'show': {'operation': ['get', 'delete', 'update'], 'resource': ['release']}}},\n            {\"name\": \"returnAll\", \"type\": NodeParameterType.BOOLEAN, \"display_name\": \"Return All\", \"default\": False, \"description\": \"Whether to return all results or only up to a given limit\", \"display_options\": {'show': {'operation': ['getAll'], 'resource': ['release']}}},\n            {\"name\": \"limit\", \"type\": NodeParameterType.NUMBER, \"display_name\": \"Limit\", \"default\": 50, \"description\": \"Max number of results to return\", \"display_options\": {'show': {'operation': ['getAll'], 'resource': ['release']}}},\n            {\"name\": \"getRepositoryIssuesFilters\", \"type\": NodeParameterType.COLLECTION, \"display_name\": \"Filters\", \"default\": \"\", \"description\": \"Return only issues which are assigned to a specific user\", \"display_options\": {'show': {'operation': ['getIssues'], 'resource': ['repository']}}},\n            {\"name\": \"getRepositoryPullRequestsFilters\", \"type\": NodeParameterType.COLLECTION, \"display_name\": \"Filters\", \"default\": \"\", \"description\": \"Returns pull requests with any state\", \"display_options\": {'show': {'operation': ['getPullRequests'], 'resource': ['repository']}}},\n            {\"name\": \"pullRequestNumber\", \"type\": NodeParameterType.NUMBER, \"display_name\": \"PR Number\", \"default\": 0, \"required\": True, \"description\": \"The number of the pull request\", \"display_options\": {'show': {'operation': ['get', 'update'], 'resource': ['review']}}},\n            {\"name\": \"reviewId\", \"type\": NodeParameterType.STRING, \"display_name\": \"Review ID\", \"default\": \"\", \"required\": True, \"description\": \"ID of the review\", \"display_options\": {'show': {'operation': ['get', 'update'], 'resource': ['review']}}},\n            {\"name\": \"event\", \"type\": NodeParameterType.OPTIONS, \"display_name\": \"Event\", \"options\": [\n                {\"name\": \"Approve\", \"value\": \"approve\"},\n                {\"name\": \"Request Change\", \"value\": \"requestChanges\"},\n                {\"name\": \"Comment\", \"value\": \"comment\"},\n                {\"name\": \"Pending\", \"value\": \"pending\"}\n            ], \"default\": \"approve\", \"description\": \"Approve the pull request\", \"display_options\": {'show': {'operation': ['create'], 'resource': ['review']}}},\n            {\"name\": \"organization\", \"type\": NodeParameterType.STRING, \"display_name\": \"Organization\", \"default\": \"\", \"required\": True, \"description\": \"The GitHub organization that the user is being invited to\", \"display_options\": {'show': {'operation': ['invite'], 'resource': ['user']}}},\n            {\"name\": \"email\", \"type\": NodeParameterType.STRING, \"display_name\": \"Email\", \"default\": \"\", \"required\": True, \"description\": \"The email address of the invited user\", \"display_options\": {'show': {'operation': ['invite'], 'resource': ['user']}}},\n            {\"name\": \"notice\", \"type\": NodeParameterType.STRING, \"display_name\": \"Only members with owner privileges for an organization or admin privileges for a repository can set up the webhooks this node requires.\", \"default\": \"\"},\n            {\"name\": \"events\", \"type\": NodeParameterType.MULTI_OPTIONS, \"display_name\": \"Events\", \"options\": [\n                {\"name\": \"*\", \"value\": \"*\"},\n                {\"name\": \"Check Run\", \"value\": \"check_run\"},\n                {\"name\": \"Check Suite\", \"value\": \"check_suite\"},\n                {\"name\": \"Commit Comment\", \"value\": \"commit_comment\"},\n                {\"name\": \"Create\", \"value\": \"create\"},\n                {\"name\": \"Delete\", \"value\": \"delete\"},\n                {\"name\": \"Deploy Key\", \"value\": \"deploy_key\"},\n                {\"name\": \"Deployment\", \"value\": \"deployment\"},\n                {\"name\": \"Deployment Status\", \"value\": \"deployment_status\"},\n                {\"name\": \"Fork\", \"value\": \"fork\"},\n                {\"name\": \"Github App Authorization\", \"value\": \"github_app_authorization\"},\n                {\"name\": \"Gollum\", \"value\": \"gollum\"},\n                {\"name\": \"Installation\", \"value\": \"installation\"},\n                {\"name\": \"Installation Repositories\", \"value\": \"installation_repositories\"},\n                {\"name\": \"Issue Comment\", \"value\": \"issue_comment\"},\n                {\"name\": \"Issues\", \"value\": \"issues\"},\n                {\"name\": \"Label\", \"value\": \"label\"},\n                {\"name\": \"Marketplace Purchase\", \"value\": \"marketplace_purchase\"},\n                {\"name\": \"Member\", \"value\": \"member\"},\n                {\"name\": \"Membership\", \"value\": \"membership\"},\n                {\"name\": \"Meta\", \"value\": \"meta\"},\n                {\"name\": \"Milestone\", \"value\": \"milestone\"},\n                {\"name\": \"Org Block\", \"value\": \"org_block\"},\n                {\"name\": \"Organization\", \"value\": \"organization\"},\n                {\"name\": \"Page Build\", \"value\": \"page_build\"},\n                {\"name\": \"Project\", \"value\": \"project\"},\n                {\"name\": \"Project Card\", \"value\": \"project_card\"},\n                {\"name\": \"Project Column\", \"value\": \"project_column\"},\n                {\"name\": \"Public\", \"value\": \"public\"},\n                {\"name\": \"Pull Request\", \"value\": \"pull_request\"},\n                {\"name\": \"Pull Request Review\", \"value\": \"pull_request_review\"},\n                {\"name\": \"Pull Request Review Comment\", \"value\": \"pull_request_review_comment\"},\n                {\"name\": \"Push\", \"value\": \"push\"},\n                {\"name\": \"Release\", \"value\": \"release\"},\n                {\"name\": \"Repository\", \"value\": \"repository\"},\n                {\"name\": \"Repository Import\", \"value\": \"repository_import\"},\n                {\"name\": \"Repository Vulnerability Alert\", \"value\": \"repository_vulnerability_alert\"},\n                {\"name\": \"Security Advisory\", \"value\": \"security_advisory\"},\n                {\"name\": \"Star\", \"value\": \"star\"},\n                {\"name\": \"Status\", \"value\": \"status\"},\n                {\"name\": \"Team\", \"value\": \"team\"},\n                {\"name\": \"Team Add\", \"value\": \"team_add\"},\n                {\"name\": \"Watch\", \"value\": \"watch\"}\n            ], \"default\": [], \"required\": True, \"description\": \"Any time any event is triggered (Wildcard Event)\"},\n            {\"name\": \"options\", \"type\": NodeParameterType.COLLECTION, \"display_name\": \"Options\", \"default\": \"\", \"description\": \"Whether the SSL certificate of the n8n host be verified by GitHub when delivering payloads\"}\n        ],\n        \"credentials\": [\n            {\"name\": \"oauth2\", \"required\": True}\n        ]\n    }\n    \n    icon = \"github.svg\"\n\n    def execute(self) -> List[List[NodeExecutionData]]:\n        \"\"\"\n        Execute the node operations.\n        \n        SYNC-CELERY SAFE: All HTTP calls use timeout parameter.\n        \n        Returns:\n            List[List[NodeExecutionData]]: Nested list where outer list is output branches,\n            inner list is items in that branch.\n        \"\"\"\n        # Get input data from previous node\n        input_data = self.get_input_data()\n        \n        # Handle empty input\n        if not input_data:\n            return [[]]\n        \n        return_items: List[NodeExecutionData] = []\n\n        for i, item in enumerate(input_data):\n            try:\n                operation = self.get_node_parameter(\"operation\", i)\n                item_data = item.json_data if hasattr(item, 'json_data') else item.get('json', {})\n                \n                if operation == \"getRepositories\":\n                    result = self._getRepositories(i, item_data)\n                elif operation == \"checkExists\":\n                    result = self._checkExists(i, item_data)\n                elif operation == \"create\":\n                    result = self._create(i, item_data)\n                elif operation == \"webhook\":\n                    result = self._webhook(i, item_data)\n                elif operation == \"getUsers\":\n                    result = self._getUsers(i, item_data)\n                elif operation == \"getRepositories\":\n                    result = self._getRepositories(i, item_data)\n                elif operation == \"getWorkflows\":\n                    result = self._getWorkflows(i, item_data)\n                elif operation == \"getRefs\":\n                    result = self._getRefs(i, item_data)\n                else:\n                    raise ValueError(f\"Unknown operation: {operation}\")\n                \n                # Handle array results\n                if isinstance(result, list):\n                    for r in result:\n                        return_items.append(NodeExecutionData(json_data=r))\n                else:\n                    return_items.append(NodeExecutionData(json_data=result))\n                    \n            except Exception as e:\n                logger.error(f\"Error in operation {operation}: {e}\")\n                if self.node_data.continue_on_fail:\n                    return_items.append(NodeExecutionData(json_data={\"error\": str(e)}))\n                else:\n                    raise\n        \n        return [return_items]\n\n    def _api_request(\n        self,\n        method: str,\n        endpoint: str,\n        body: Dict[str, Any] | None = None,\n        query: Dict[str, Any] | None = None,\n    ) -> Dict[str, Any]:\n        \"\"\"\n        Make authenticated API request.\n        \n        SYNC-CELERY SAFE: Uses requests with timeout.\n        \"\"\"\n        credentials = self.get_credentials(\"oauth2\")\n        \n        # Build headers based on credential type\n        headers = {}\n        if credentials.get(\"accessToken\"):\n            headers[\"Authorization\"] = f\"Bot {credentials.get('accessToken')}\"\n        elif credentials.get(\"apiKey\"):\n            query = query or {}\n            query[\"api_key\"] = credentials.get(\"apiKey\")\n        \n        url = f\"https://api.github.com/repos/test-owner/test-repo{endpoint}\"\n        \n        response = requests.request(\n            method,\n            url,\n            params=query,\n            json=body,\n            headers=headers,\n            timeout=30,  # REQUIRED for Celery\n        )\n        response.raise_for_status()\n        return response.json()\n\n    def _getRepositories(self, item_index: int, item_data: Dict[str, Any]) -> Dict[str, Any]:\n        \"\"\"\n        getRepositories operation.\n        \n        Args:\n            item_index: Index of the current item being processed\n            item_data: JSON data from the input item\n            \n        Returns:\n            Dict with operation result\n            \n        TODO: Implement operation logic.\n        \"\"\"\n        # TODO: Extract parameters using item_index\n        # param = self.get_node_parameter(\"paramName\", item_index)\n        \n        # TODO: Make API call\n        # response = self._api_request(\"GET\", \"/endpoint\", query={\"param\": param})\n        \n        raise NotImplementedError(\"getRepositories operation not implemented\")\n\n    def _checkExists(self, item_index: int, item_data: Dict[str, Any]) -> Dict[str, Any]:\n        \"\"\"\n        checkExists operation.\n        \n        Args:\n            item_index: Index of the current item being processed\n            item_data: JSON data from the input item\n            \n        Returns:\n            Dict with operation result\n            \n        TODO: Implement operation logic.\n        \"\"\"\n        # TODO: Extract parameters using item_index\n        # param = self.get_node_parameter(\"paramName\", item_index)\n        \n        # TODO: Make API call\n        # response = self._api_request(\"GET\", \"/endpoint\", query={\"param\": param})\n        \n        raise NotImplementedError(\"checkExists operation not implemented\")\n\n    def _create(self, item_index: int, item_data: Dict[str, Any]) -> Dict[str, Any]:\n        \"\"\"\n        create operation.\n        \n        Args:\n            item_index: Index of the current item being processed\n            item_data: JSON data from the input item\n            \n        Returns:\n            Dict with operation result\n            \n        TODO: Implement operation logic.\n        \"\"\"\n        # TODO: Extract parameters using item_index\n        # param = self.get_node_parameter(\"paramName\", item_index)\n        \n        # TODO: Make API call\n        # response = self._api_request(\"GET\", \"/endpoint\", query={\"param\": param})\n        \n        raise NotImplementedError(\"create operation not implemented\")\n\n    def _webhook(self, item_index: int, item_data: Dict[str, Any]) -> Dict[str, Any]:\n        \"\"\"\n        webhook operation.\n        \n        Args:\n            item_index: Index of the current item being processed\n            item_data: JSON data from the input item\n            \n        Returns:\n            Dict with operation result\n            \n        TODO: Implement operation logic.\n        \"\"\"\n        # TODO: Extract parameters using item_index\n        # param = self.get_node_parameter(\"paramName\", item_index)\n        \n        # TODO: Make API call\n        # response = self._api_request(\"GET\", \"/endpoint\", query={\"param\": param})\n        \n        raise NotImplementedError(\"webhook operation not implemented\")\n\n    def _getUsers(self, item_index: int, item_data: Dict[str, Any]) -> Dict[str, Any]:\n        \"\"\"\n        getUsers operation.\n        \n        Args:\n            item_index: Index of the current item being processed\n            item_data: JSON data from the input item\n            \n        Returns:\n            Dict with operation result\n            \n        TODO: Implement operation logic.\n        \"\"\"\n        # TODO: Extract parameters using item_index\n        # param = self.get_node_parameter(\"paramName\", item_index)\n        \n        # TODO: Make API call\n        # response = self._api_request(\"GET\", \"/endpoint\", query={\"param\": param})\n        \n        raise NotImplementedError(\"getUsers operation not implemented\")\n\n    def _getRepositories(self, item_index: int, item_data: Dict[str, Any]) -> Dict[str, Any]:\n        \"\"\"\n        getRepositories operation.\n        \n        Args:\n            item_index: Index of the current item being processed\n            item_data: JSON data from the input item\n            \n        Returns:\n            Dict with operation result\n            \n        TODO: Implement operation logic.\n        \"\"\"\n        # TODO: Extract parameters using item_index\n        # param = self.get_node_parameter(\"paramName\", item_index)\n        \n        # TODO: Make API call\n        # response = self._api_request(\"GET\", \"/endpoint\", query={\"param\": param})\n        \n        raise NotImplementedError(\"getRepositories operation not implemented\")\n\n    def _getWorkflows(self, item_index: int, item_data: Dict[str, Any]) -> Dict[str, Any]:\n        \"\"\"\n        getWorkflows operation.\n        \n        Args:\n            item_index: Index of the current item being processed\n            item_data: JSON data from the input item\n            \n        Returns:\n            Dict with operation result\n            \n        TODO: Implement operation logic.\n        \"\"\"\n        # TODO: Extract parameters using item_index\n        # param = self.get_node_parameter(\"paramName\", item_index)\n        \n        # TODO: Make API call\n        # response = self._api_request(\"GET\", \"/endpoint\", query={\"param\": param})\n        \n        raise NotImplementedError(\"getWorkflows operation not implemented\")\n\n    def _getRefs(self, item_index: int, item_data: Dict[str, Any]) -> Dict[str, Any]:\n        \"\"\"\n        getRefs operation.\n        \n        Args:\n            item_index: Index of the current item being processed\n            item_data: JSON data from the input item\n            \n        Returns:\n            Dict with operation result\n            \n        TODO: Implement operation logic.\n        \"\"\"\n        # TODO: Extract parameters using item_index\n        # param = self.get_node_parameter(\"paramName\", item_index)\n        \n        # TODO: Make API call\n        # response = self._api_request(\"GET\", \"/endpoint\", query={\"param\": param})\n        \n        raise NotImplementedError(\"getRefs operation not implemented\")\n\n",
    "__init__.py": "\"\"\"\nGithub Node Package\nConverted from TypeScript by agent-skills/code-convert\n\"\"\"\n\nfrom .github import GithubNode\n\n__all__ = [\"GithubNode\"]\n"
  },
  "node_schema": {
    "type": "node",
    "version": 1,
    "description": {
      "displayName": "Node",
      "name": "node",
      "inputs": [
        {
          "name": "main",
          "type": "main"
        }
      ],
      "outputs": [
        {
          "name": "main",
          "type": "main"
        }
      ]
    },
    "properties": {
      "parameters": [
        {
          "name": "operation",
          "type": "OPTIONS",
          "display_name": "Operation",
          "options": [
            {
              "name": "Get Repositories",
              "value": "getRepositories",
              "description": "Returns all repositories of an organization"
            },
            {
              "name": "checkExists",
              "value": "checkExists",
              "description": "Operation: checkExists"
            },
            {
              "name": "create",
              "value": "create",
              "description": "Operation: create"
            },
            {
              "name": "webhook",
              "value": "webhook",
              "description": "Operation: webhook"
            },
            {
              "name": "getUsers",
              "value": "getUsers",
              "description": "Operation: getUsers"
            },
            {
              "name": "getRepositories",
              "value": "getRepositories",
              "description": "Operation: getRepositories"
            },
            {
              "name": "getWorkflows",
              "value": "getWorkflows",
              "description": "Operation: getWorkflows"
            },
            {
              "name": "getRefs",
              "value": "getRefs",
              "description": "Operation: getRefs"
            }
          ],
          "default": "getRepositories",
          "description": "Operation to perform"
        },
        {
          "name": "authentication",
          "display_name": "Authentication",
          "type": "OPTIONS",
          "default": "accessToken",
          "options": [
            {
              "name": "Access Token",
              "value": "accessToken"
            },
            {
              "name": "OAuth2",
              "value": "oAuth2"
            }
          ]
        },
        {
          "name": "webhookNotice",
          "display_name": "Your execution will pause until a webhook is called. This URL will be generated at runtime and passed to your Github workflow as a resumeUrl input.",
          "type": "NOTICE",
          "default": "",
          "display_options": {
            "show": {
              "operation": [
                "dispatchAndWait"
              ],
              "resource": [
                "workflow"
              ]
            }
          }
        },
        {
          "name": "owner",
          "display_name": "Repository Owner",
          "type": "RESOURCELOCATOR",
          "default": "",
          "required": true
        },
        {
          "name": "repository",
          "display_name": "Repository Name",
          "type": "RESOURCELOCATOR",
          "default": "",
          "required": true
        },
        {
          "name": "workflowId",
          "display_name": "Workflow",
          "type": "RESOURCELOCATOR",
          "default": "",
          "required": true,
          "description": "The workflow to dispatch",
          "display_options": {
            "show": {
              "operation": [
                "disable",
                "dispatch",
                "dispatchAndWait",
                "get",
                "getUsage",
                "enable"
              ],
              "resource": [
                "workflow"
              ]
            }
          }
        },
        {
          "name": "ref",
          "display_name": "Ref",
          "type": "STRING",
          "default": "main",
          "required": true,
          "description": "The git reference for the workflow dispatch (branch or tag name)",
          "display_options": {
            "show": {
              "operation": [
                "dispatch",
                "dispatchAndWait"
              ],
              "resource": [
                "workflow"
              ]
            }
          }
        },
        {
          "name": "inputs",
          "display_name": "Inputs",
          "type": "JSON",
          "default": "{}",
          "description": "JSON object with input parameters for the workflow",
          "display_options": {
            "show": {
              "operation": [
                "dispatch",
                "dispatchAndWait"
              ],
              "resource": [
                "workflow"
              ]
            }
          }
        },
        {
          "name": "filePath",
          "display_name": "File Path",
          "type": "STRING",
          "default": "",
          "required": true,
          "description": "The file path of the file. Has to contain the full path.",
          "display_options": {
            "show": {
              "resource": [
                "file"
              ]
            }
          }
        },
        {
          "name": "binaryData",
          "display_name": "Binary File",
          "type": "BOOLEAN",
          "default": false,
          "required": true,
          "description": "Whether the data to upload should be taken from binary field",
          "display_options": {
            "show": {
              "operation": [
                "create",
                "edit"
              ],
              "resource": [
                "file"
              ]
            }
          }
        },
        {
          "name": "fileContent",
          "display_name": "File Content",
          "type": "STRING",
          "default": "",
          "required": true,
          "description": "The text content of the file",
          "display_options": {
            "show": {
              "operation": [
                "create",
                "edit"
              ],
              "resource": [
                "file"
              ]
            }
          }
        },
        {
          "name": "binaryPropertyName",
          "display_name": "Input Binary Field",
          "type": "STRING",
          "default": "data",
          "required": true,
          "display_options": {
            "show": {
              "operation": [
                "create",
                "edit"
              ],
              "resource": [
                "file"
              ]
            }
          }
        },
        {
          "name": "commitMessage",
          "display_name": "Commit Message",
          "type": "STRING",
          "default": "",
          "required": true,
          "display_options": {
            "show": {
              "operation": [
                "create",
                "delete",
                "edit"
              ],
              "resource": [
                "file"
              ]
            }
          }
        },
        {
          "name": "additionalParameters",
          "display_name": "Additional Parameters",
          "type": "COLLECTION",
          "default": "",
          "description": "Additional fields to add",
          "display_options": {
            "show": {
              "operation": [
                "create",
                "delete",
                "edit"
              ],
              "resource": [
                "file"
              ]
            }
          }
        },
        {
          "name": "asBinaryProperty",
          "display_name": "As Binary Property",
          "type": "BOOLEAN",
          "default": true,
          "description": "Whether to set the data of the file as binary property instead of returning the raw API response",
          "display_options": {
            "show": {
              "operation": [
                "get"
              ],
              "resource": [
                "file"
              ]
            }
          }
        },
        {
          "name": "title",
          "display_name": "Title",
          "type": "STRING",
          "default": "",
          "required": true,
          "description": "The title of the issue",
          "display_options": {
            "show": {
              "operation": [
                "create"
              ],
              "resource": [
                "issue"
              ]
            }
          }
        },
        {
          "name": "body",
          "display_name": "Body",
          "type": "STRING",
          "default": "",
          "description": "The body of the issue",
          "display_options": {
            "show": {
              "operation": [
                "create"
              ],
              "resource": [
                "issue"
              ]
            }
          }
        },
        {
          "name": "labels",
          "display_name": "Labels",
          "type": "COLLECTION",
          "default": "",
          "description": "Label to add to issue",
          "display_options": {
            "show": {
              "operation": [
                "create"
              ],
              "resource": [
                "issue"
              ]
            }
          }
        },
        {
          "name": "assignees",
          "display_name": "Assignees",
          "type": "COLLECTION",
          "default": "",
          "description": "User to assign issue too",
          "display_options": {
            "show": {
              "operation": [
                "create"
              ],
              "resource": [
                "issue"
              ]
            }
          }
        },
        {
          "name": "issueNumber",
          "display_name": "Issue Number",
          "type": "NUMBER",
          "default": 0,
          "required": true,
          "description": "The number of the issue on which to create the comment on",
          "display_options": {
            "show": {
              "operation": [
                "createComment"
              ],
              "resource": [
                "issue"
              ]
            }
          }
        },
        {
          "name": "editFields",
          "display_name": "Edit Fields",
          "type": "COLLECTION",
          "default": "",
          "description": "User to assign issue to",
          "display_options": {
            "show": {
              "operation": [
                "edit"
              ],
              "resource": [
                "issue"
              ]
            }
          }
        },
        {
          "name": "lockReason",
          "display_name": "Lock Reason",
          "type": "OPTIONS",
          "default": "resolved",
          "description": "The issue is Off-Topic",
          "display_options": {
            "show": {
              "operation": [
                "lock"
              ],
              "resource": [
                "issue"
              ]
            }
          },
          "options": [
            {
              "name": "Off-Topic",
              "value": "off-topic"
            },
            {
              "name": "Too Heated",
              "value": "too heated"
            },
            {
              "name": "Resolved",
              "value": "resolved"
            },
            {
              "name": "Spam",
              "value": "spam"
            }
          ]
        },
        {
          "name": "releaseTag",
          "display_name": "Tag",
          "type": "STRING",
          "default": "",
          "required": true,
          "description": "The tag of the release",
          "display_options": {
            "show": {
              "operation": [
                "create"
              ],
              "resource": [
                "release"
              ]
            }
          }
        },
        {
          "name": "additionalFields",
          "display_name": "Additional Fields",
          "type": "COLLECTION",
          "default": "",
          "description": "The name of the issue",
          "display_options": {
            "show": {
              "operation": [
                "create"
              ],
              "resource": [
                "release"
              ]
            }
          }
        },
        {
          "name": "release_id",
          "display_name": "Release ID",
          "type": "STRING",
          "default": "",
          "required": true,
          "display_options": {
            "show": {
              "operation": [
                "get",
                "delete",
                "update"
              ],
              "resource": [
                "release"
              ]
            }
          }
        },
        {
          "name": "returnAll",
          "display_name": "Return All",
          "type": "BOOLEAN",
          "default": false,
          "description": "Whether to return all results or only up to a given limit",
          "display_options": {
            "show": {
              "operation": [
                "getAll"
              ],
              "resource": [
                "release"
              ]
            }
          }
        },
        {
          "name": "limit",
          "display_name": "Limit",
          "type": "NUMBER",
          "default": 50,
          "description": "Max number of results to return",
          "display_options": {
            "show": {
              "operation": [
                "getAll"
              ],
              "resource": [
                "release"
              ]
            }
          }
        },
        {
          "name": "getRepositoryIssuesFilters",
          "display_name": "Filters",
          "type": "COLLECTION",
          "default": "",
          "description": "Return only issues which are assigned to a specific user",
          "display_options": {
            "show": {
              "operation": [
                "getIssues"
              ],
              "resource": [
                "repository"
              ]
            }
          }
        },
        {
          "name": "getRepositoryPullRequestsFilters",
          "display_name": "Filters",
          "type": "COLLECTION",
          "default": "",
          "description": "Returns pull requests with any state",
          "display_options": {
            "show": {
              "operation": [
                "getPullRequests"
              ],
              "resource": [
                "repository"
              ]
            }
          }
        },
        {
          "name": "pullRequestNumber",
          "display_name": "PR Number",
          "type": "NUMBER",
          "default": 0,
          "required": true,
          "description": "The number of the pull request",
          "display_options": {
            "show": {
              "operation": [
                "get",
                "update"
              ],
              "resource": [
                "review"
              ]
            }
          }
        },
        {
          "name": "reviewId",
          "display_name": "Review ID",
          "type": "STRING",
          "default": "",
          "required": true,
          "description": "ID of the review",
          "display_options": {
            "show": {
              "operation": [
                "get",
                "update"
              ],
              "resource": [
                "review"
              ]
            }
          }
        },
        {
          "name": "event",
          "display_name": "Event",
          "type": "OPTIONS",
          "default": "approve",
          "description": "Approve the pull request",
          "display_options": {
            "show": {
              "operation": [
                "create"
              ],
              "resource": [
                "review"
              ]
            }
          },
          "options": [
            {
              "name": "Approve",
              "value": "approve"
            },
            {
              "name": "Request Change",
              "value": "requestChanges"
            },
            {
              "name": "Comment",
              "value": "comment"
            },
            {
              "name": "Pending",
              "value": "pending"
            }
          ]
        },
        {
          "name": "organization",
          "display_name": "Organization",
          "type": "STRING",
          "default": "",
          "required": true,
          "description": "The GitHub organization that the user is being invited to",
          "display_options": {
            "show": {
              "operation": [
                "invite"
              ],
              "resource": [
                "user"
              ]
            }
          }
        },
        {
          "name": "email",
          "display_name": "Email",
          "type": "STRING",
          "default": "",
          "required": true,
          "description": "The email address of the invited user",
          "display_options": {
            "show": {
              "operation": [
                "invite"
              ],
              "resource": [
                "user"
              ]
            }
          }
        },
        {
          "name": "notice",
          "display_name": "Only members with owner privileges for an organization or admin privileges for a repository can set up the webhooks this node requires.",
          "type": "NOTICE",
          "default": ""
        },
        {
          "name": "events",
          "display_name": "Events",
          "type": "MULTIOPTIONS",
          "default": [],
          "required": true,
          "description": "Any time any event is triggered (Wildcard Event)",
          "options": [
            {
              "name": "*",
              "value": "*"
            },
            {
              "name": "Check Run",
              "value": "check_run"
            },
            {
              "name": "Check Suite",
              "value": "check_suite"
            },
            {
              "name": "Commit Comment",
              "value": "commit_comment"
            },
            {
              "name": "Create",
              "value": "create"
            },
            {
              "name": "Delete",
              "value": "delete"
            },
            {
              "name": "Deploy Key",
              "value": "deploy_key"
            },
            {
              "name": "Deployment",
              "value": "deployment"
            },
            {
              "name": "Deployment Status",
              "value": "deployment_status"
            },
            {
              "name": "Fork",
              "value": "fork"
            },
            {
              "name": "Github App Authorization",
              "value": "github_app_authorization"
            },
            {
              "name": "Gollum",
              "value": "gollum"
            },
            {
              "name": "Installation",
              "value": "installation"
            },
            {
              "name": "Installation Repositories",
              "value": "installation_repositories"
            },
            {
              "name": "Issue Comment",
              "value": "issue_comment"
            },
            {
              "name": "Issues",
              "value": "issues"
            },
            {
              "name": "Label",
              "value": "label"
            },
            {
              "name": "Marketplace Purchase",
              "value": "marketplace_purchase"
            },
            {
              "name": "Member",
              "value": "member"
            },
            {
              "name": "Membership",
              "value": "membership"
            },
            {
              "name": "Meta",
              "value": "meta"
            },
            {
              "name": "Milestone",
              "value": "milestone"
            },
            {
              "name": "Org Block",
              "value": "org_block"
            },
            {
              "name": "Organization",
              "value": "organization"
            },
            {
              "name": "Page Build",
              "value": "page_build"
            },
            {
              "name": "Project",
              "value": "project"
            },
            {
              "name": "Project Card",
              "value": "project_card"
            },
            {
              "name": "Project Column",
              "value": "project_column"
            },
            {
              "name": "Public",
              "value": "public"
            },
            {
              "name": "Pull Request",
              "value": "pull_request"
            },
            {
              "name": "Pull Request Review",
              "value": "pull_request_review"
            },
            {
              "name": "Pull Request Review Comment",
              "value": "pull_request_review_comment"
            },
            {
              "name": "Push",
              "value": "push"
            },
            {
              "name": "Release",
              "value": "release"
            },
            {
              "name": "Repository",
              "value": "repository"
            },
            {
              "name": "Repository Import",
              "value": "repository_import"
            },
            {
              "name": "Repository Vulnerability Alert",
              "value": "repository_vulnerability_alert"
            },
            {
              "name": "Security Advisory",
              "value": "security_advisory"
            },
            {
              "name": "Star",
              "value": "star"
            },
            {
              "name": "Status",
              "value": "status"
            },
            {
              "name": "Team",
              "value": "team"
            },
            {
              "name": "Team Add",
              "value": "team_add"
            },
            {
              "name": "Watch",
              "value": "watch"
            }
          ]
        },
        {
          "name": "options",
          "display_name": "Options",
          "type": "COLLECTION",
          "default": "",
          "description": "Whether the SSL certificate of the n8n host be verified by GitHub when delivering payloads"
        }
      ],
      "credentials": [
        "oauth2"
      ]
    },
    "operations": [
      {
        "name": "getRepositories",
        "display_name": "Get Repositories",
        "description": "Returns all repositories of an organization"
      },
      {
        "name": "checkExists",
        "description": "Operation: checkExists"
      },
      {
        "name": "create",
        "description": "Operation: create"
      },
      {
        "name": "webhook",
        "description": "Operation: webhook"
      },
      {
        "name": "getUsers",
        "description": "Operation: getUsers"
      },
      {
        "name": "getRepositories",
        "description": "Operation: getRepositories"
      },
      {
        "name": "getWorkflows",
        "description": "Operation: getWorkflows"
      },
      {
        "name": "getRefs",
        "description": "Operation: getRefs"
      }
    ],
    "resources": [],
    "credentials": [
      "oauth2"
    ]
  },
  "trace_map": {
    "correlation_id": "node-github-009",
    "node_type": "node",
    "trace_entries": [
      {
        "field_path": "operations[6].name",
        "source": "SOURCE_CODE",
        "evidence": "n8n operation 'getRepositories' (display: 'Get Repositories') in Github.node.ts",
        "confidence": "high",
        "source_file": "Github.node.ts",
        "line_range": "L141",
        "excerpt_hash": "6b82a17354ab"
      },
      {
        "field_path": "operations[1].name",
        "source": "SOURCE_CODE",
        "evidence": "Function 'checkExists' defined in GithubTrigger.node.ts",
        "confidence": "high",
        "source_file": "GithubTrigger.node.ts",
        "line_range": "L459",
        "excerpt_hash": "5be11dd57b5f"
      },
      {
        "field_path": "operations[2].name",
        "source": "SOURCE_CODE",
        "evidence": "Function 'create' defined in GithubTrigger.node.ts",
        "confidence": "high",
        "source_file": "GithubTrigger.node.ts",
        "line_range": "L491",
        "excerpt_hash": "537a3dc6a4d7"
      },
      {
        "field_path": "operations[3].name",
        "source": "SOURCE_CODE",
        "evidence": "Function 'webhook' defined in GithubTrigger.node.ts",
        "confidence": "high",
        "source_file": "GithubTrigger.node.ts",
        "line_range": "L611",
        "excerpt_hash": "d4d633bde3c3"
      },
      {
        "field_path": "operations[4].name",
        "source": "SOURCE_CODE",
        "evidence": "Function 'getUsers' defined in SearchFunctions.ts",
        "confidence": "high",
        "source_file": "SearchFunctions.ts",
        "line_range": "L33",
        "excerpt_hash": "acb150b818af"
      },
      {
        "field_path": "operations[5].name",
        "source": "SOURCE_CODE",
        "evidence": "Function 'getRepositories' defined in SearchFunctions.ts",
        "confidence": "high",
        "source_file": "SearchFunctions.ts",
        "line_range": "L68",
        "excerpt_hash": "0ad2a01442a6"
      },
      {
        "field_path": "operations[6].name",
        "source": "SOURCE_CODE",
        "evidence": "Function 'getWorkflows' defined in SearchFunctions.ts",
        "confidence": "high",
        "source_file": "SearchFunctions.ts",
        "line_range": "L104",
        "excerpt_hash": "8985deabe145"
      },
      {
        "field_path": "operations[7].name",
        "source": "SOURCE_CODE",
        "evidence": "Function 'getRefs' defined in SearchFunctions.ts",
        "confidence": "high",
        "source_file": "SearchFunctions.ts",
        "line_range": "L133",
        "excerpt_hash": "a77f95c7d15e"
      },
      {
        "field_path": "credentials[0]",
        "source": "SOURCE_CODE",
        "evidence": "Auth pattern 'oauth' found in source",
        "confidence": "medium"
      }
    ],
    "generated_at": "2026-01-06T08:30:21.460185",
    "skill_version": "1.0.0",
    "_hybrid_metadata": {
      "source_type": "TYPE1",
      "extraction_confidence": 0.8333333333333333,
      "advisor_used": false,
      "assumption_ratio": 0.0,
      "deterministic_operations": 9,
      "assumption_operations": 0
    }
  },
  "tests_passed": false,
  "validation_passed": true,
  "fix_iterations": 0,
  "source_files": [],
  "source_hash": null
}