{
  "correlation_id": "gitlab-final-test-001",
  "node_type": null,
  "skill_name": "code-convert",
  "created_at": "2026-02-02T14:49:01.441596",
  "generated_code": {
    "gitlab.py": "#!/usr/bin/env python3\n\"\"\"\nGitlab Node\n\nConverted from TypeScript by agent-skills/code-convert\nCorrelation ID: gitlab-final-test-001\nGenerated: 2026-02-02T14:49:01.415376\n\nSYNC-CELERY SAFE: All methods are synchronous with timeouts.\n\"\"\"\n\nfrom __future__ import annotations\n\nimport logging\nfrom typing import Any, Dict, List\n\nimport requests\n\nfrom .base import BaseNode, NodeParameter, NodeParameterType, NodeExecutionData\n\nlogger = logging.getLogger(__name__)\n\n\nclass GitlabNode(BaseNode):\n    \"\"\"\n    Gitlab node.\n    \n    \n    \"\"\"\n\n    node_type = \"gitlab\"\n    node_version = 1\n    display_name = \"Gitlab\"\n    description = \"\"\n    icon = \"file:gitlab.svg\"\n    group = ['output']\n    \n    credentials = [\n        {\n            \"name\": \"gitlabApi\",\n            \"required\": True,\n        }\n    ]\n\n    properties = [\n            {\"name\": \"authentication\", \"type\": NodeParameterType.OPTIONS, \"display_name\": \"Authentication\", \"options\": [\n                {\"name\": \"Gitlabapi\", \"value\": \"gitlabApi\"},\n                {\"name\": \"Gitlaboauth2api\", \"value\": \"gitlabOAuth2Api\"}\n            ], \"default\": \"gitlabApi\", \"description\": \"Authentication method to use\"},\n            {\"name\": \"resource\", \"type\": NodeParameterType.OPTIONS, \"display_name\": \"Resource\", \"options\": [\n                {\"name\": \"Issue\", \"value\": \"issue\"},\n                {\"name\": \"Repository\", \"value\": \"repository\"},\n                {\"name\": \"User\", \"value\": \"user\"},\n                {\"name\": \"Release\", \"value\": \"release\"},\n                {\"name\": \"File\", \"value\": \"file\"}\n            ], \"default\": \"issue\", \"description\": \"The resource to operate on\"},\n            {\"name\": \"operation\", \"type\": NodeParameterType.OPTIONS, \"display_name\": \"Operation\", \"options\": [\n                {\"name\": \"Create\", \"value\": \"create\", \"description\": \"Create file\"},\n                {\"name\": \"Delete\", \"value\": \"delete\", \"description\": \"Delete file\"},\n                {\"name\": \"Get\", \"value\": \"get\", \"description\": \"Get file\"},\n                {\"name\": \"Get Many\", \"value\": \"getAll\", \"description\": \"Get many files\"},\n                {\"name\": \"Update\", \"value\": \"update\", \"description\": \"Update file\"}\n            ], \"default\": \"create\", \"description\": \"Operation to perform on file\", \"display_options\": {'show': {'resource': ['file']}}},\n            {\"name\": \"operation\", \"type\": NodeParameterType.OPTIONS, \"display_name\": \"Operation\", \"options\": [\n                {\"name\": \"Create\", \"value\": \"create\", \"description\": \"Create release\"},\n                {\"name\": \"Delete\", \"value\": \"delete\", \"description\": \"Delete release\"},\n                {\"name\": \"Get\", \"value\": \"get\", \"description\": \"Get release\"},\n                {\"name\": \"Get Many\", \"value\": \"getAll\", \"description\": \"Get many releases\"},\n                {\"name\": \"Update\", \"value\": \"update\", \"description\": \"Update release\"}\n            ], \"default\": \"create\", \"description\": \"Operation to perform on release\", \"display_options\": {'show': {'resource': ['release']}}},\n            {\"name\": \"operation\", \"type\": NodeParameterType.OPTIONS, \"display_name\": \"Operation\", \"options\": [\n                {\"name\": \"Create\", \"value\": \"create\", \"description\": \"Create user\"},\n                {\"name\": \"Delete\", \"value\": \"delete\", \"description\": \"Delete user\"},\n                {\"name\": \"Get\", \"value\": \"get\", \"description\": \"Get user\"},\n                {\"name\": \"Get Many\", \"value\": \"getAll\", \"description\": \"Get many users\"},\n                {\"name\": \"Update\", \"value\": \"update\", \"description\": \"Update user\"}\n            ], \"default\": \"create\", \"description\": \"Operation to perform on user\", \"display_options\": {'show': {'resource': ['user']}}},\n            {\"name\": \"operation\", \"type\": NodeParameterType.OPTIONS, \"display_name\": \"Operation\", \"options\": [\n                {\"name\": \"Create\", \"value\": \"create\", \"description\": \"Create repository\"},\n                {\"name\": \"Delete\", \"value\": \"delete\", \"description\": \"Delete repository\"},\n                {\"name\": \"Get\", \"value\": \"get\", \"description\": \"Get repository\"},\n                {\"name\": \"Get Many\", \"value\": \"getAll\", \"description\": \"Get many repositorys\"},\n                {\"name\": \"Update\", \"value\": \"update\", \"description\": \"Update repository\"}\n            ], \"default\": \"create\", \"description\": \"Operation to perform on repository\", \"display_options\": {'show': {'resource': ['repository']}}},\n            {\"name\": \"operation\", \"type\": NodeParameterType.OPTIONS, \"display_name\": \"Operation\", \"options\": [\n                {\"name\": \"Create\", \"value\": \"create\", \"description\": \"Create issue\"},\n                {\"name\": \"Delete\", \"value\": \"delete\", \"description\": \"Delete issue\"},\n                {\"name\": \"Get\", \"value\": \"get\", \"description\": \"Get issue\"},\n                {\"name\": \"Get Many\", \"value\": \"getAll\", \"description\": \"Get many issues\"},\n                {\"name\": \"Update\", \"value\": \"update\", \"description\": \"Update issue\"}\n            ], \"default\": \"create\", \"description\": \"Operation to perform on issue\", \"display_options\": {'show': {'resource': ['issue']}}},\n            {\"name\": \"Issue\", \"type\": NodeParameterType.OPTIONS, \"display_name\": \"File\"},\n            {\"name\": \"Create Comment\", \"type\": NodeParameterType.OPTIONS, \"display_name\": \"Create\", \"description\": \"Create a new issue\"},\n            {\"name\": \"Get Issues\", \"type\": NodeParameterType.OPTIONS, \"display_name\": \"Get\", \"description\": \"Get the data of a single repository\"},\n            {\"name\": \"Delete\", \"type\": NodeParameterType.OPTIONS, \"display_name\": \"Create\", \"description\": \"Create a new release\"},\n            {\"name\": \"Delete\", \"type\": NodeParameterType.STRING, \"display_name\": \"Create\", \"description\": \"Create a new file in repository\"},\n            {\"name\": \"repository\", \"type\": NodeParameterType.STRING, \"display_name\": \"Project Name\", \"default\": \"\", \"required\": True, \"description\": \"The name of the project\"},\n            {\"name\": \"title\", \"type\": NodeParameterType.STRING, \"display_name\": \"Title\", \"default\": \"\", \"required\": True, \"description\": \"The title of the issue\", \"display_options\": {'show': {'operation': ['create']}}},\n            {\"name\": \"body\", \"type\": NodeParameterType.STRING, \"display_name\": \"Body\", \"default\": \"\", \"description\": \"The body of the issue\", \"display_options\": {'show': {'operation': ['create']}}},\n            {\"name\": \"due_date\", \"type\": NodeParameterType.STRING, \"display_name\": \"Due Date\", \"default\": \"\", \"description\": \"Due Date for issue\", \"display_options\": {'show': {'operation': ['create']}}},\n            {\"name\": \"labels\", \"type\": NodeParameterType.COLLECTION, \"display_name\": \"Labels\", \"default\": \"{ label: \", \"description\": \"Label to add to issue\", \"display_options\": {'show': {'operation': ['create']}}},\n            {\"name\": \"label\", \"type\": NodeParameterType.STRING, \"display_name\": \"Label\", \"default\": \"\", \"description\": \"Label to add to issue\"},\n            {\"name\": \"assignee_ids\", \"type\": NodeParameterType.COLLECTION, \"display_name\": \"Assignees\", \"default\": \"{ assignee: \", \"description\": \"User ID to assign issue to\", \"display_options\": {'show': {'operation': ['create']}}},\n            {\"name\": \"assignee\", \"type\": NodeParameterType.NUMBER, \"display_name\": \"Assignee\", \"default\": 0, \"description\": \"User ID to assign issue to\"},\n            {\"name\": \"issueNumber\", \"type\": NodeParameterType.NUMBER, \"display_name\": \"Issue Number\", \"default\": 0, \"required\": True, \"description\": \"The number of the issue on which to create the comment on\", \"display_options\": {'show': {'operation': ['createComment']}}},\n            {\"name\": \"body\", \"type\": NodeParameterType.STRING, \"display_name\": \"Body\", \"default\": \"\", \"description\": \"The body of the comment\", \"display_options\": {'show': {'operation': ['createComment']}}},\n            {\"name\": \"issueNumber\", \"type\": NodeParameterType.NUMBER, \"display_name\": \"Issue Number\", \"default\": 0, \"required\": True, \"description\": \"The number of the issue edit\", \"display_options\": {'show': {'operation': ['edit']}}},\n            {\"name\": \"editFields\", \"type\": NodeParameterType.COLLECTION, \"display_name\": \"Edit Fields\", \"default\": \"{\", \"description\": \"The title of the issue\", \"display_options\": {'show': {'operation': ['edit']}}},\n            {\"name\": \"title\", \"type\": NodeParameterType.STRING, \"display_name\": \"Title\", \"default\": \"\", \"description\": \"The title of the issue\"},\n            {\"name\": \"description\", \"type\": NodeParameterType.STRING, \"display_name\": \"Body\", \"default\": \"\", \"description\": \"The body of the issue\"},\n            {\"name\": \"state\", \"type\": NodeParameterType.OPTIONS, \"display_name\": \"State\", \"options\": [\n                {\"name\": \"Closed\", \"value\": \"closed\"},\n                {\"name\": \"Open\", \"value\": \"open\"}\n            ], \"default\": \"open\", \"description\": \"Set the state to \"},\n            {\"name\": \"Open\", \"type\": NodeParameterType.COLLECTION, \"display_name\": \"Closed\", \"description\": \"Set the state to \"},\n            {\"name\": \"label\", \"type\": NodeParameterType.STRING, \"display_name\": \"Label\", \"default\": \"\", \"description\": \"Label to add to issue\"},\n            {\"name\": \"assignee_ids\", \"type\": NodeParameterType.COLLECTION, \"display_name\": \"Assignees\", \"default\": \"{ assignee: \", \"description\": \"User to assign issue too\"},\n            {\"name\": \"assignee\", \"type\": NodeParameterType.STRING, \"display_name\": \"Assignees\", \"default\": \"\", \"description\": \"User to assign issue too\"},\n            {\"name\": \"due_date\", \"type\": NodeParameterType.STRING, \"display_name\": \"Due Date\", \"default\": \"\", \"description\": \"Due Date for issue\"},\n            {\"name\": \"issueNumber\", \"type\": NodeParameterType.NUMBER, \"display_name\": \"Issue Number\", \"default\": 0, \"required\": True, \"description\": \"The number of the issue get data of\", \"display_options\": {'show': {'operation': ['get']}}},\n            {\"name\": \"issueNumber\", \"type\": NodeParameterType.NUMBER, \"display_name\": \"Issue Number\", \"default\": 0, \"required\": True, \"description\": \"The number of the issue to lock\", \"display_options\": {'show': {'operation': ['lock']}}},\n            {\"name\": \"lockReason\", \"type\": NodeParameterType.OPTIONS, \"display_name\": \"Lock Reason\", \"options\": [\n                {\"name\": \"Off-Topic\", \"value\": \"off-topic\"},\n                {\"name\": \"Too Heated\", \"value\": \"too heated\"},\n                {\"name\": \"Resolved\", \"value\": \"resolved\"},\n                {\"name\": \"Spam\", \"value\": \"spam\"}\n            ], \"default\": \"resolved\", \"description\": \"The issue is Off-Topic\", \"display_options\": {'show': {'operation': ['lock']}}},\n            {\"name\": \"Too Heated\", \"type\": NodeParameterType.STRING, \"display_name\": \"Off-Topic\", \"description\": \"The issue is Off-Topic\"},\n            {\"name\": \"additionalFields\", \"type\": NodeParameterType.COLLECTION, \"display_name\": \"Additional Fields\", \"default\": \"{\", \"description\": \"The name of the release\", \"display_options\": {'show': {'operation': ['create']}}},\n            {\"name\": \"name\", \"type\": NodeParameterType.STRING, \"display_name\": \"Name\", \"default\": \"\", \"description\": \"The name of the release\"},\n            {\"name\": \"description\", \"type\": NodeParameterType.STRING, \"display_name\": \"Description\", \"default\": \"\", \"description\": \"The description of the release\"},\n            {\"name\": \"ref\", \"type\": NodeParameterType.STRING, \"display_name\": \"Ref\", \"default\": \"\", \"description\": \"If Tag doesn\u2019t exist, the release will be created from Ref. It can be a commit SHA, another tag name, or a branch name.\"},\n            {\"name\": \"projectId\", \"type\": NodeParameterType.STRING, \"display_name\": \"Project ID\", \"default\": \"\", \"required\": True, \"description\": \"The ID or URL-encoded path of the project\", \"display_options\": {'show': {'operation': ['delete', 'get']}}},\n            {\"name\": \"tag_name\", \"type\": NodeParameterType.STRING, \"display_name\": \"Tag Name\", \"default\": \"\", \"required\": True, \"description\": \"The Git tag the release is associated with\", \"display_options\": {'show': {'operation': ['delete', 'get']}}},\n            {\"name\": \"projectId\", \"type\": NodeParameterType.STRING, \"display_name\": \"Project ID\", \"default\": \"\", \"required\": True, \"description\": \"The ID or URL-encoded path of the project\", \"display_options\": {'show': {'operation': ['getAll']}}},\n            {\"name\": \"returnAll\", \"type\": NodeParameterType.BOOLEAN, \"display_name\": \"Return All\", \"default\": False, \"description\": \"Whether to return all results or only up to a given limit\", \"display_options\": {'show': {'operation': ['getAll', 'list', 'getIssues']}}},\n            {\"name\": \"limit\", \"type\": NodeParameterType.NUMBER, \"display_name\": \"Limit\", \"default\": 20, \"description\": \"Max number of results to return\", \"display_options\": {'show': {'operation': ['getAll', 'list', 'getIssues']}}},\n            {\"name\": \"additionalFields\", \"type\": NodeParameterType.COLLECTION, \"display_name\": \"Additional Fields\", \"default\": \"{\", \"description\": \"The field to use\", \"display_options\": {'show': {'operation': ['getAll']}}},\n            {\"name\": \"order_by\", \"type\": NodeParameterType.OPTIONS, \"display_name\": \"Order By\", \"options\": [\n                {\"name\": \"Created At\", \"value\": \"created_at\"},\n                {\"name\": \"Released At\", \"value\": \"released_at\"}\n            ], \"default\": \"released_at\", \"description\": \"The field to use\"},\n            {\"name\": \"Released At\", \"type\": NodeParameterType.OPTIONS, \"display_name\": \"Created At\"},\n            {\"name\": \"DESC\", \"type\": NodeParameterType.STRING, \"display_name\": \"ASC\"},\n            {\"name\": \"tag_name\", \"type\": NodeParameterType.STRING, \"display_name\": \"Tag Name\", \"default\": \"\", \"required\": True, \"description\": \"The Git tag the release is associated with\", \"display_options\": {'show': {'operation': ['update']}}},\n            {\"name\": \"additionalFields\", \"type\": NodeParameterType.COLLECTION, \"display_name\": \"Additional Fields\", \"default\": \"{\", \"description\": \"The release name\", \"display_options\": {'show': {'operation': ['update']}}},\n            {\"name\": \"name\", \"type\": NodeParameterType.STRING, \"display_name\": \"Name\", \"default\": \"\", \"description\": \"The release name\"},\n            {\"name\": \"description\", \"type\": NodeParameterType.STRING, \"display_name\": \"Description\", \"default\": \"\", \"description\": \"The description of the release. You can use Markdown.\"},\n            {\"name\": \"milestones\", \"type\": NodeParameterType.STRING, \"display_name\": \"Milestones\", \"default\": \"\", \"description\": \"The title of each milestone to associate with the release (provide a titles list spearated with comma)\"},\n            {\"name\": \"released_at\", \"type\": NodeParameterType.STRING, \"display_name\": \"Released At\", \"default\": \"\", \"description\": \"The date when the release is/was ready\"},\n            {\"name\": \"getRepositoryIssuesFilters\", \"type\": NodeParameterType.COLLECTION, \"display_name\": \"Filters\", \"default\": \"{\", \"description\": \"Return only issues which are assigned to a specific user\", \"display_options\": {'show': {'operation': ['getIssues']}}},\n            {\"name\": \"assignee_username\", \"type\": NodeParameterType.STRING, \"display_name\": \"Assignee\", \"default\": \"\", \"description\": \"Return only issues which are assigned to a specific user\"},\n            {\"name\": \"author_username\", \"type\": NodeParameterType.STRING, \"display_name\": \"Creator\", \"default\": \"\", \"description\": \"Return only issues which were created by a specific user\"},\n            {\"name\": \"search\", \"type\": NodeParameterType.STRING, \"display_name\": \"Search\", \"default\": \"\", \"description\": \"Search issues against their title and description\"},\n            {\"name\": \"labels\", \"type\": NodeParameterType.STRING, \"display_name\": \"Labels\", \"default\": \"\", \"description\": \"Return only issues with the given labels. Multiple lables can be separated by comma.\"},\n            {\"name\": \"updated_after\", \"type\": NodeParameterType.STRING, \"display_name\": \"Updated After\", \"default\": \"\", \"description\": \"Return only issues updated at or after this time\"},\n            {\"name\": \"state\", \"type\": NodeParameterType.OPTIONS, \"display_name\": \"State\", \"options\": [\n                {\"name\": \"All\", \"value\": \"closed\"},\n                {\"name\": \"Open\", \"value\": \"opened\"}\n            ], \"default\": \"opened\", \"description\": \"Returns issues with any state\"},\n            {\"name\": \"Closed\", \"type\": NodeParameterType.OPTIONS, \"display_name\": \"All\", \"description\": \"Returns issues with any state\"},\n            {\"name\": \"Updated At\", \"type\": NodeParameterType.OPTIONS, \"display_name\": \"Created At\", \"description\": \"Sort by created date\"},\n            {\"name\": \"Descending\", \"type\": NodeParameterType.STRING, \"display_name\": \"Ascending\", \"description\": \"Sort in ascending order\"},\n            {\"name\": \"filePath\", \"type\": NodeParameterType.STRING, \"display_name\": \"Path\", \"default\": \"\", \"description\": \"The path of the folder to list\", \"display_options\": {'show': {'operation': ['list']}}},\n            {\"name\": \"page\", \"type\": NodeParameterType.NUMBER, \"display_name\": \"Page\", \"default\": 1, \"description\": \"Page of results to display\", \"display_options\": {'show': {'operation': ['list']}}},\n            {\"name\": \"additionalParameters\", \"type\": NodeParameterType.COLLECTION, \"display_name\": \"Additional Parameters\", \"default\": \"{\", \"description\": \"Additional fields to add\", \"display_options\": {'show': {'operation': ['list']}}},\n            {\"name\": \"ref\", \"type\": NodeParameterType.STRING, \"display_name\": \"Reference\", \"default\": \"\", \"description\": \"The name of the commit/branch/tag. Default: the repository\u2019s default branch (usually main).\"},\n            {\"name\": \"recursive\", \"type\": NodeParameterType.BOOLEAN, \"display_name\": \"Recursive\", \"default\": False, \"description\": \"Whether or not to get a recursive file tree. Default is False.\"},\n            {\"name\": \"asBinaryProperty\", \"type\": NodeParameterType.BOOLEAN, \"display_name\": \"As Binary Property\", \"default\": True, \"description\": \"Whether to set the data of the file property instead of returning the raw API response\", \"display_options\": {'show': {'operation': ['get']}}},\n            {\"name\": \"binaryPropertyName\", \"type\": NodeParameterType.STRING, \"display_name\": \"Put Output File in Field\", \"default\": \"data\", \"required\": True, \"display_options\": {'show': {'operation': ['get']}}},\n            {\"name\": \"additionalParameters\", \"type\": NodeParameterType.COLLECTION, \"display_name\": \"Additional Parameters\", \"default\": \"{\", \"description\": \"Additional fields to add\", \"display_options\": {'show': {'operation': ['get']}}},\n            {\"name\": \"reference\", \"type\": NodeParameterType.STRING, \"display_name\": \"Reference\", \"default\": \"\", \"description\": \"The name of the commit/branch/tag. Default: the repository\u2019s default branch (usually main).\"},\n            {\"name\": \"binaryData\", \"type\": NodeParameterType.BOOLEAN, \"display_name\": \"Binary File\", \"default\": False, \"required\": True, \"description\": \"Whether the data to upload should be taken from binary field\", \"display_options\": {'show': {'operation': ['create', 'edit']}}},\n            {\"name\": \"fileContent\", \"type\": NodeParameterType.STRING, \"display_name\": \"File Content\", \"default\": \"\", \"required\": True, \"description\": \"The text content of the file\", \"display_options\": {'show': {'operation': ['create', 'edit']}}},\n            {\"name\": \"binaryPropertyName\", \"type\": NodeParameterType.STRING, \"display_name\": \"Input Binary Field\", \"default\": \"data\", \"required\": True, \"display_options\": {'show': {'operation': ['create', 'edit']}}},\n            {\"name\": \"commitMessage\", \"type\": NodeParameterType.STRING, \"display_name\": \"Commit Message\", \"default\": \"\", \"required\": True, \"display_options\": {'show': {'operation': ['create', 'delete', 'edit']}}},\n            {\"name\": \"branch\", \"type\": NodeParameterType.STRING, \"display_name\": \"Branch\", \"default\": \"\", \"required\": True, \"description\": \"Name of the new branch to create. The commit is added to this branch.\", \"display_options\": {'show': {'operation': ['create', 'delete', 'edit']}}},\n            {\"name\": \"additionalParameters\", \"type\": NodeParameterType.COLLECTION, \"display_name\": \"Additional Parameters\", \"default\": \"{\", \"description\": \"Additional fields to add\", \"display_options\": {'show': {'operation': ['create', 'delete', 'edit']}}},\n            {\"name\": \"branchStart\", \"type\": NodeParameterType.STRING, \"display_name\": \"Start Branch\", \"default\": \"\", \"description\": \"Name of the base branch to create the new branch from\"},\n            {\"name\": \"name\", \"type\": NodeParameterType.STRING, \"display_name\": \"author\", \"default\": \"\", \"description\": \"The name of the author of the commit\"},\n            {\"name\": \"email\", \"type\": NodeParameterType.STRING, \"display_name\": \"Email\", \"default\": \"\", \"description\": \"The email of the author of the commit\"},\n            {\"name\": \"encoding\", \"type\": NodeParameterType.STRING, \"display_name\": \"encoding\", \"default\": \"text\", \"description\": \"Change encoding to base64. Default is text.\"},\n            {\"name\": \"repository\", \"type\": NodeParameterType.STRING, \"display_name\": \"Repository Name\", \"default\": \"\", \"required\": True, \"description\": \"The name of the repository\"},\n            {\"name\": \"events\", \"type\": NodeParameterType.MULTI_OPTIONS, \"display_name\": \"Events\", \"options\": [\n                {\"name\": \"*\", \"value\": \"*\"}\n            ], \"default\": \"[]\", \"required\": True, \"description\": \"Any time any event is triggered (Wildcard Event)\"}\n        ]\n\n    def execute(self) -> List[List[NodeExecutionData]]:\n        \"\"\"\n        Execute the node operations.\n        \n        SYNC-CELERY SAFE: All HTTP calls use timeout parameter.\n        \n        Returns:\n            List[List[NodeExecutionData]]: Nested list where outer list is output branches,\n            inner list is items in that branch.\n        \"\"\"\n        # Get input data from previous node\n        input_data = self.get_input_data()\n        \n        # Handle empty input\n        if not input_data:\n            return [[]]\n        \n        return_items: List[NodeExecutionData] = []\n\n        for i, item in enumerate(input_data):\n            try:\n                resource = self.get_node_parameter(\"resource\", i)\n                operation = self.get_node_parameter(\"operation\", i)\n                item_data = item.json_data if hasattr(item, 'json_data') else item.get('json', {})\n                \n                if resource == \"issue\" and operation == \"create\":\n                    result = self._issue_create(i, item_data)\n                elif resource == \"issue\" and operation == \"createComment\":\n                    result = self._issue_createComment(i, item_data)\n                elif resource == \"issue\" and operation == \"edit\":\n                    result = self._issue_edit(i, item_data)\n                elif resource == \"issue\" and operation == \"get\":\n                    result = self._issue_get(i, item_data)\n                elif resource == \"issue\" and operation == \"lock\":\n                    result = self._issue_lock(i, item_data)\n                elif resource == \"release\" and operation == \"create\":\n                    result = self._release_create(i, item_data)\n                elif resource == \"release\" and operation == \"delete\":\n                    result = self._release_delete(i, item_data)\n                elif resource == \"release\" and operation == \"get\":\n                    result = self._release_get(i, item_data)\n                elif resource == \"release\" and operation == \"getAll\":\n                    result = self._release_getAll(i, item_data)\n                elif resource == \"release\" and operation == \"update\":\n                    result = self._release_update(i, item_data)\n                elif resource == \"repository\" and operation == \"get\":\n                    result = self._repository_get(i, item_data)\n                elif resource == \"repository\" and operation == \"getIssues\":\n                    result = self._repository_getIssues(i, item_data)\n                elif resource == \"user\" and operation == \"getRepositories\":\n                    result = self._user_getRepositories(i, item_data)\n                elif resource == \"file\" and operation == \"delete\":\n                    result = self._file_delete(i, item_data)\n                elif resource == \"file\" and operation == \"get\":\n                    result = self._file_get(i, item_data)\n                elif resource == \"file\" and operation == \"list\":\n                    result = self._file_list(i, item_data)\n                else:\n                    raise ValueError(f\"Unknown resource/operation: {resource}/{operation}\")\n                \n                # Handle array results\n                if isinstance(result, list):\n                    for r in result:\n                        return_items.append(NodeExecutionData(json_data=r))\n                else:\n                    return_items.append(NodeExecutionData(json_data=result))\n                \n            except Exception:\n                logger.error(f\"Error in {resource}/{operation}: {e}\")\n                if self.continue_on_fail:\n                    return_items.append(NodeExecutionData(json_data={\"error\": str(e)}))\n                else:\n                    raise\n        \n        return [return_items]\n\n    def _api_request(\n        self,\n        method: str,\n        endpoint: str,\n        body: Dict[str, Any] | None = None,\n        query: Dict[str, Any] | None = None,\n    ) -> Dict[str, Any]:\n        \"\"\"\n        Make authenticated API request.\n        \n        SYNC-CELERY SAFE: Uses requests with timeout.\n        \"\"\"\n        credentials = self.get_credentials(\"gitlabApi\")\n        \n        # TODO: Configure authentication based on credential type\n        query = query or {}\n        # For API key auth: query[\"api_key\"] = credentials.get(\"apiKey\")\n        # For Bearer auth: headers[\"Authorization\"] = f\"Bearer {credentials.get('accessToken')}\"\n        \n        url = f\"https://api.example.com{endpoint}\"\n        \n        response = requests.request(\n            method,\n            url,\n            params=query,\n            json=body,\n            timeout=30,  # REQUIRED for Celery\n        )\n        response.raise_for_status()\n        return response.json()\n\n    def _issue_create(self, item_index: int, item_data: Dict[str, Any]) -> Dict[str, Any]:\n        \"\"\"\n        Issue Create operation.\n        \n        Args:\n            item_index: Index of the current item being processed\n            item_data: JSON data from the input item\n            \n        Returns:\n            Dict with operation result\n        \"\"\"\n        title = self.get_node_parameter('title', item_index)\n        description = self.get_node_parameter('body', item_index)\n        due_date = self.get_node_parameter('due_date', item_index)\n        labels = self.get_node_parameter('labels', item_index)\n        assignee_ids = self.get_node_parameter('assignee_ids', item_index)\n        \n        # TODO: Implement API call\n        response = {}\n        \n        return response\n\n    def _issue_createComment(self, item_index: int, item_data: Dict[str, Any]) -> Dict[str, Any]:\n        \"\"\"\n        Issue Createcomment operation.\n        \n        Args:\n            item_index: Index of the current item being processed\n            item_data: JSON data from the input item\n            \n        Returns:\n            Dict with operation result\n        \"\"\"\n        issue_number = self.get_node_parameter('issueNumber', item_index)\n        body = self.get_node_parameter('body', item_index)\n        \n        # TODO: Implement API call\n        response = {}\n        \n        return response\n\n    def _issue_edit(self, item_index: int, item_data: Dict[str, Any]) -> Dict[str, Any]:\n        \"\"\"\n        Issue Edit operation.\n        \n        Args:\n            item_index: Index of the current item being processed\n            item_data: JSON data from the input item\n            \n        Returns:\n            Dict with operation result\n        \"\"\"\n        issue_number = self.get_node_parameter('issueNumber', item_index)\n        body = self.get_node_parameter('editFields', item_index)\n        \n        # TODO: Implement API call\n        response = {}\n        \n        return response\n\n    def _issue_get(self, item_index: int, item_data: Dict[str, Any]) -> Dict[str, Any]:\n        \"\"\"\n        Issue Get operation.\n        \n        Args:\n            item_index: Index of the current item being processed\n            item_data: JSON data from the input item\n            \n        Returns:\n            Dict with operation result\n        \"\"\"\n        issue_number = self.get_node_parameter('issueNumber', item_index)\n        \n        # TODO: Implement API call\n        response = {}\n        \n        return response\n\n    def _issue_lock(self, item_index: int, item_data: Dict[str, Any]) -> Dict[str, Any]:\n        \"\"\"\n        Issue Lock operation.\n        \n        Args:\n            item_index: Index of the current item being processed\n            item_data: JSON data from the input item\n            \n        Returns:\n            Dict with operation result\n        \"\"\"\n        issue_number = self.get_node_parameter('issueNumber', item_index)\n        \n        # Build request body\n        body = {'discussion_locked': True}\n        \n        # TODO: Implement API call\n        response = {}\n        \n        return response\n\n    def _release_create(self, item_index: int, item_data: Dict[str, Any]) -> Dict[str, Any]:\n        \"\"\"\n        Release Create operation.\n        \n        Args:\n            item_index: Index of the current item being processed\n            item_data: JSON data from the input item\n            \n        Returns:\n            Dict with operation result\n        \"\"\"\n        body = self.get_node_parameter('additionalFields', item_index)\n        tag_name = self.get_node_parameter('releaseTag', item_index)\n        \n        # TODO: Implement API call\n        response = {}\n        \n        return response\n\n    def _release_delete(self, item_index: int, item_data: Dict[str, Any]) -> Dict[str, Any]:\n        \"\"\"\n        Release Delete operation.\n        \n        Args:\n            item_index: Index of the current item being processed\n            item_data: JSON data from the input item\n            \n        Returns:\n            Dict with operation result\n        \"\"\"\n        id = self.get_node_parameter('projectId', item_index)\n        tag_name = self.get_node_parameter('tag_name', item_index)\n        \n        # TODO: Implement API call\n        response = {}\n        \n        return response\n\n    def _release_get(self, item_index: int, item_data: Dict[str, Any]) -> Dict[str, Any]:\n        \"\"\"\n        Release Get operation.\n        \n        Args:\n            item_index: Index of the current item being processed\n            item_data: JSON data from the input item\n            \n        Returns:\n            Dict with operation result\n        \"\"\"\n        id = self.get_node_parameter('projectId', item_index)\n        tag_name = self.get_node_parameter('tag_name', item_index)\n        \n        # TODO: Implement API call\n        response = {}\n        \n        return response\n\n    def _release_getAll(self, item_index: int, item_data: Dict[str, Any]) -> Dict[str, Any]:\n        \"\"\"\n        Release Getall operation.\n        \n        Args:\n            item_index: Index of the current item being processed\n            item_data: JSON data from the input item\n            \n        Returns:\n            Dict with operation result\n        \"\"\"\n        id = self.get_node_parameter('projectId', item_index)\n        qs = self.get_node_parameter('additionalFields', item_index)\n        return_all = self.get_node_parameter('returnAll', item_index)\n        per_page = self.get_node_parameter('limit', item_index)\n        \n        # Build query parameters\n        query = {}\n        query['per_page'] = this_get_node_parameter('limit', 0)\n        \n        # TODO: Implement API call\n        response = {}\n        \n        return response\n\n    def _release_update(self, item_index: int, item_data: Dict[str, Any]) -> Dict[str, Any]:\n        \"\"\"\n        Release Update operation.\n        \n        Args:\n            item_index: Index of the current item being processed\n            item_data: JSON data from the input item\n            \n        Returns:\n            Dict with operation result\n        \"\"\"\n        id = self.get_node_parameter('projectId', item_index)\n        tag_name = self.get_node_parameter('tag_name', item_index)\n        body = self.get_node_parameter('additionalFields', item_index)\n        \n        # TODO: Implement API call\n        response = {}\n        \n        return response\n\n    def _repository_get(self, item_index: int, item_data: Dict[str, Any]) -> Dict[str, Any]:\n        \"\"\"\n        Repository Get operation.\n        \n        Args:\n            item_index: Index of the current item being processed\n            item_data: JSON data from the input item\n            \n        Returns:\n            Dict with operation result\n        \"\"\"\n        \n        # TODO: Implement API call\n        response = {}\n        \n        return response\n\n    def _repository_getIssues(self, item_index: int, item_data: Dict[str, Any]) -> Dict[str, Any]:\n        \"\"\"\n        Repository Getissues operation.\n        \n        Args:\n            item_index: Index of the current item being processed\n            item_data: JSON data from the input item\n            \n        Returns:\n            Dict with operation result\n        \"\"\"\n        qs = self.get_node_parameter('getRepositoryIssuesFilters', item_index)\n        return_all = self.get_node_parameter('returnAll', item_index)\n        per_page = self.get_node_parameter('limit', item_index)\n        \n        # Build query parameters\n        query = {}\n        query['per_page'] = this_get_node_parameter('limit', 0)\n        \n        # TODO: Implement API call\n        response = {}\n        \n        return response\n\n    def _user_getRepositories(self, item_index: int, item_data: Dict[str, Any]) -> Dict[str, Any]:\n        \"\"\"\n        User Getrepositories operation.\n        \n        Args:\n            item_index: Index of the current item being processed\n            item_data: JSON data from the input item\n            \n        Returns:\n            Dict with operation result\n        \"\"\"\n        \n        # TODO: Implement API call\n        response = {}\n        \n        return response\n\n    def _file_delete(self, item_index: int, item_data: Dict[str, Any]) -> Dict[str, Any]:\n        \"\"\"\n        File Delete operation.\n        \n        Args:\n            item_index: Index of the current item being processed\n            item_data: JSON data from the input item\n            \n        Returns:\n            Dict with operation result\n        \"\"\"\n        branch = self.get_node_parameter('branch', item_index)\n        commit_message = self.get_node_parameter('commitMessage', item_index)\n        file_path = self.get_node_parameter('filePath', item_index)\n        \n        # Build request body\n        body = {'author_name': author_name, 'author_email': author_email}\n        \n        # TODO: Implement API call\n        response = {}\n        \n        return response\n\n    def _file_get(self, item_index: int, item_data: Dict[str, Any]) -> Dict[str, Any]:\n        \"\"\"\n        File Get operation.\n        \n        Args:\n            item_index: Index of the current item being processed\n            item_data: JSON data from the input item\n            \n        Returns:\n            Dict with operation result\n        \"\"\"\n        file_path = self.get_node_parameter('filePath', item_index)\n        \n        # Build query parameters\n        query = {}\n        query['ref'] = additional_parameters_reference\n        query['ref'] = 'master'\n        \n        # TODO: Implement API call\n        response = {}\n        \n        return response\n\n    def _file_list(self, item_index: int, item_data: Dict[str, Any]) -> Dict[str, Any]:\n        \"\"\"\n        File List operation.\n        \n        Args:\n            item_index: Index of the current item being processed\n            item_data: JSON data from the input item\n            \n        Returns:\n            Dict with operation result\n        \"\"\"\n        file_path = self.get_node_parameter('filePath', item_index)\n        qs = self.get_node_parameter('additionalParameters', item_index)\n        return_all = self.get_node_parameter('returnAll', item_index)\n        per_page = self.get_node_parameter('limit', item_index)\n        page = self.get_node_parameter('page', item_index)\n        \n        # Build query parameters\n        query = {}\n        query['per_page'] = this_get_node_parameter('limit', i)\n        query['page'] = this_get_node_parameter('page', i)\n        query['path'] = file_path\n        \n        # TODO: Implement API call\n        response = {}\n        \n        return response\n\n",
    "__init__.py": "\"\"\"\nGitlab Node Package\nConverted from TypeScript by agent-skills/code-convert\n\"\"\"\n\nfrom .gitlab import GitlabNode\n\n__all__ = [\"GitlabNode\"]\n"
  },
  "node_schema": {
    "type": "Gitlab",
    "version": 1,
    "description": {
      "displayName": "Gitlab",
      "name": "gitlab",
      "inputs": [
        {
          "name": "main",
          "type": "main"
        }
      ],
      "outputs": [
        {
          "name": "main",
          "type": "main"
        }
      ]
    },
    "properties": {
      "parameters": [
        {
          "name": "authentication",
          "type": "OPTIONS",
          "display_name": "Authentication",
          "options": [
            {
              "name": "Gitlabapi",
              "value": "gitlabApi"
            },
            {
              "name": "Gitlaboauth2api",
              "value": "gitlabOAuth2Api"
            }
          ],
          "default": "gitlabApi",
          "description": "Authentication method to use"
        },
        {
          "name": "resource",
          "type": "OPTIONS",
          "display_name": "Resource",
          "options": [
            {
              "name": "Issue",
              "value": "issue"
            },
            {
              "name": "Repository",
              "value": "repository"
            },
            {
              "name": "User",
              "value": "user"
            },
            {
              "name": "Release",
              "value": "release"
            },
            {
              "name": "File",
              "value": "file"
            }
          ],
          "default": "issue",
          "description": "The resource to operate on"
        },
        {
          "name": "operation",
          "type": "OPTIONS",
          "display_name": "Operation",
          "options": [
            {
              "name": "Create",
              "value": "create",
              "description": "Create file"
            },
            {
              "name": "Delete",
              "value": "delete",
              "description": "Delete file"
            },
            {
              "name": "Get",
              "value": "get",
              "description": "Get file"
            },
            {
              "name": "Get Many",
              "value": "getAll",
              "description": "Get many files"
            },
            {
              "name": "Update",
              "value": "update",
              "description": "Update file"
            }
          ],
          "default": "create",
          "description": "Operation to perform on file",
          "display_options": {
            "show": {
              "resource": [
                "file"
              ]
            }
          }
        },
        {
          "name": "operation",
          "type": "OPTIONS",
          "display_name": "Operation",
          "options": [
            {
              "name": "Create",
              "value": "create",
              "description": "Create release"
            },
            {
              "name": "Delete",
              "value": "delete",
              "description": "Delete release"
            },
            {
              "name": "Get",
              "value": "get",
              "description": "Get release"
            },
            {
              "name": "Get Many",
              "value": "getAll",
              "description": "Get many releases"
            },
            {
              "name": "Update",
              "value": "update",
              "description": "Update release"
            }
          ],
          "default": "create",
          "description": "Operation to perform on release",
          "display_options": {
            "show": {
              "resource": [
                "release"
              ]
            }
          }
        },
        {
          "name": "operation",
          "type": "OPTIONS",
          "display_name": "Operation",
          "options": [
            {
              "name": "Create",
              "value": "create",
              "description": "Create user"
            },
            {
              "name": "Delete",
              "value": "delete",
              "description": "Delete user"
            },
            {
              "name": "Get",
              "value": "get",
              "description": "Get user"
            },
            {
              "name": "Get Many",
              "value": "getAll",
              "description": "Get many users"
            },
            {
              "name": "Update",
              "value": "update",
              "description": "Update user"
            }
          ],
          "default": "create",
          "description": "Operation to perform on user",
          "display_options": {
            "show": {
              "resource": [
                "user"
              ]
            }
          }
        },
        {
          "name": "operation",
          "type": "OPTIONS",
          "display_name": "Operation",
          "options": [
            {
              "name": "Create",
              "value": "create",
              "description": "Create repository"
            },
            {
              "name": "Delete",
              "value": "delete",
              "description": "Delete repository"
            },
            {
              "name": "Get",
              "value": "get",
              "description": "Get repository"
            },
            {
              "name": "Get Many",
              "value": "getAll",
              "description": "Get many repositorys"
            },
            {
              "name": "Update",
              "value": "update",
              "description": "Update repository"
            }
          ],
          "default": "create",
          "description": "Operation to perform on repository",
          "display_options": {
            "show": {
              "resource": [
                "repository"
              ]
            }
          }
        },
        {
          "name": "operation",
          "type": "OPTIONS",
          "display_name": "Operation",
          "options": [
            {
              "name": "Create",
              "value": "create",
              "description": "Create issue"
            },
            {
              "name": "Delete",
              "value": "delete",
              "description": "Delete issue"
            },
            {
              "name": "Get",
              "value": "get",
              "description": "Get issue"
            },
            {
              "name": "Get Many",
              "value": "getAll",
              "description": "Get many issues"
            },
            {
              "name": "Update",
              "value": "update",
              "description": "Update issue"
            }
          ],
          "default": "create",
          "description": "Operation to perform on issue",
          "display_options": {
            "show": {
              "resource": [
                "issue"
              ]
            }
          }
        },
        {
          "name": "Issue",
          "display_name": "File",
          "type": "OPTIONS"
        },
        {
          "name": "Create Comment",
          "display_name": "Create",
          "type": "OPTIONS",
          "description": "Create a new issue"
        },
        {
          "name": "Get Issues",
          "display_name": "Get",
          "type": "OPTIONS",
          "description": "Get the data of a single repository"
        },
        {
          "name": "Delete",
          "display_name": "Create",
          "type": "OPTIONS",
          "description": "Create a new release"
        },
        {
          "name": "Delete",
          "display_name": "Create",
          "type": "STRING",
          "description": "Create a new file in repository"
        },
        {
          "name": "repository",
          "display_name": "Project Name",
          "type": "STRING",
          "default": "",
          "required": true,
          "description": "The name of the project"
        },
        {
          "name": "title",
          "display_name": "Title",
          "type": "STRING",
          "default": "",
          "required": true,
          "description": "The title of the issue",
          "display_options": {
            "show": {
              "operation": [
                "create"
              ]
            }
          }
        },
        {
          "name": "body",
          "display_name": "Body",
          "type": "STRING",
          "default": "",
          "description": "The body of the issue",
          "display_options": {
            "show": {
              "operation": [
                "create"
              ]
            }
          }
        },
        {
          "name": "due_date",
          "display_name": "Due Date",
          "type": "DATETIME",
          "default": "",
          "description": "Due Date for issue",
          "display_options": {
            "show": {
              "operation": [
                "create"
              ]
            }
          }
        },
        {
          "name": "labels",
          "display_name": "Labels",
          "type": "COLLECTION",
          "default": "{ label: ",
          "description": "Label to add to issue",
          "display_options": {
            "show": {
              "operation": [
                "create"
              ]
            }
          }
        },
        {
          "name": "label",
          "display_name": "Label",
          "type": "STRING",
          "default": "",
          "description": "Label to add to issue"
        },
        {
          "name": "assignee_ids",
          "display_name": "Assignees",
          "type": "COLLECTION",
          "default": "{ assignee: ",
          "description": "User ID to assign issue to",
          "display_options": {
            "show": {
              "operation": [
                "create"
              ]
            }
          }
        },
        {
          "name": "assignee",
          "display_name": "Assignee",
          "type": "NUMBER",
          "default": 0,
          "description": "User ID to assign issue to"
        },
        {
          "name": "issueNumber",
          "display_name": "Issue Number",
          "type": "NUMBER",
          "default": 0,
          "required": true,
          "description": "The number of the issue on which to create the comment on",
          "display_options": {
            "show": {
              "operation": [
                "createComment"
              ]
            }
          }
        },
        {
          "name": "body",
          "display_name": "Body",
          "type": "STRING",
          "default": "",
          "description": "The body of the comment",
          "display_options": {
            "show": {
              "operation": [
                "createComment"
              ]
            }
          }
        },
        {
          "name": "issueNumber",
          "display_name": "Issue Number",
          "type": "NUMBER",
          "default": 0,
          "required": true,
          "description": "The number of the issue edit",
          "display_options": {
            "show": {
              "operation": [
                "edit"
              ]
            }
          }
        },
        {
          "name": "editFields",
          "display_name": "Edit Fields",
          "type": "COLLECTION",
          "default": "{",
          "description": "The title of the issue",
          "display_options": {
            "show": {
              "operation": [
                "edit"
              ]
            }
          }
        },
        {
          "name": "title",
          "display_name": "Title",
          "type": "STRING",
          "default": "",
          "description": "The title of the issue"
        },
        {
          "name": "description",
          "display_name": "Body",
          "type": "STRING",
          "default": "",
          "description": "The body of the issue"
        },
        {
          "name": "state",
          "display_name": "State",
          "type": "OPTIONS",
          "default": "open",
          "description": "Set the state to ",
          "options": [
            {
              "name": "Closed",
              "value": "closed"
            },
            {
              "name": "Open",
              "value": "open"
            }
          ]
        },
        {
          "name": "Open",
          "display_name": "Closed",
          "type": "COLLECTION",
          "description": "Set the state to "
        },
        {
          "name": "label",
          "display_name": "Label",
          "type": "STRING",
          "default": "",
          "description": "Label to add to issue"
        },
        {
          "name": "assignee_ids",
          "display_name": "Assignees",
          "type": "COLLECTION",
          "default": "{ assignee: ",
          "description": "User to assign issue too"
        },
        {
          "name": "assignee",
          "display_name": "Assignees",
          "type": "STRING",
          "default": "",
          "description": "User to assign issue too"
        },
        {
          "name": "due_date",
          "display_name": "Due Date",
          "type": "DATETIME",
          "default": "",
          "description": "Due Date for issue"
        },
        {
          "name": "issueNumber",
          "display_name": "Issue Number",
          "type": "NUMBER",
          "default": 0,
          "required": true,
          "description": "The number of the issue get data of",
          "display_options": {
            "show": {
              "operation": [
                "get"
              ]
            }
          }
        },
        {
          "name": "issueNumber",
          "display_name": "Issue Number",
          "type": "NUMBER",
          "default": 0,
          "required": true,
          "description": "The number of the issue to lock",
          "display_options": {
            "show": {
              "operation": [
                "lock"
              ]
            }
          }
        },
        {
          "name": "lockReason",
          "display_name": "Lock Reason",
          "type": "OPTIONS",
          "default": "resolved",
          "description": "The issue is Off-Topic",
          "display_options": {
            "show": {
              "operation": [
                "lock"
              ]
            }
          },
          "options": [
            {
              "name": "Off-Topic",
              "value": "off-topic"
            },
            {
              "name": "Too Heated",
              "value": "too heated"
            },
            {
              "name": "Resolved",
              "value": "resolved"
            },
            {
              "name": "Spam",
              "value": "spam"
            }
          ]
        },
        {
          "name": "Too Heated",
          "display_name": "Off-Topic",
          "type": "STRING",
          "description": "The issue is Off-Topic"
        },
        {
          "name": "additionalFields",
          "display_name": "Additional Fields",
          "type": "COLLECTION",
          "default": "{",
          "description": "The name of the release",
          "display_options": {
            "show": {
              "operation": [
                "create"
              ]
            }
          }
        },
        {
          "name": "name",
          "display_name": "Name",
          "type": "STRING",
          "default": "",
          "description": "The name of the release"
        },
        {
          "name": "description",
          "display_name": "Description",
          "type": "STRING",
          "default": "",
          "description": "The description of the release"
        },
        {
          "name": "ref",
          "display_name": "Ref",
          "type": "STRING",
          "default": "",
          "description": "If Tag doesn\u2019t exist, the release will be created from Ref. It can be a commit SHA, another tag name, or a branch name."
        },
        {
          "name": "projectId",
          "display_name": "Project ID",
          "type": "STRING",
          "default": "",
          "required": true,
          "description": "The ID or URL-encoded path of the project",
          "display_options": {
            "show": {
              "operation": [
                "delete",
                "get"
              ]
            }
          }
        },
        {
          "name": "tag_name",
          "display_name": "Tag Name",
          "type": "STRING",
          "default": "",
          "required": true,
          "description": "The Git tag the release is associated with",
          "display_options": {
            "show": {
              "operation": [
                "delete",
                "get"
              ]
            }
          }
        },
        {
          "name": "projectId",
          "display_name": "Project ID",
          "type": "STRING",
          "default": "",
          "required": true,
          "description": "The ID or URL-encoded path of the project",
          "display_options": {
            "show": {
              "operation": [
                "getAll"
              ]
            }
          }
        },
        {
          "name": "returnAll",
          "display_name": "Return All",
          "type": "BOOLEAN",
          "default": false,
          "description": "Whether to return all results or only up to a given limit",
          "display_options": {
            "show": {
              "operation": [
                "getAll",
                "list",
                "getIssues"
              ]
            }
          }
        },
        {
          "name": "limit",
          "display_name": "Limit",
          "type": "NUMBER",
          "default": 20,
          "description": "Max number of results to return",
          "display_options": {
            "show": {
              "operation": [
                "getAll",
                "list",
                "getIssues"
              ]
            }
          }
        },
        {
          "name": "additionalFields",
          "display_name": "Additional Fields",
          "type": "COLLECTION",
          "default": "{",
          "description": "The field to use as order",
          "display_options": {
            "show": {
              "operation": [
                "getAll"
              ]
            }
          }
        },
        {
          "name": "order_by",
          "display_name": "Order By",
          "type": "OPTIONS",
          "default": "released_at",
          "description": "The field to use as order",
          "options": [
            {
              "name": "Created At",
              "value": "created_at"
            },
            {
              "name": "Released At",
              "value": "released_at"
            }
          ]
        },
        {
          "name": "Released At",
          "display_name": "Created At",
          "type": "OPTIONS"
        },
        {
          "name": "DESC",
          "display_name": "ASC",
          "type": "STRING"
        },
        {
          "name": "tag_name",
          "display_name": "Tag Name",
          "type": "STRING",
          "default": "",
          "required": true,
          "description": "The Git tag the release is associated with",
          "display_options": {
            "show": {
              "operation": [
                "update"
              ]
            }
          }
        },
        {
          "name": "additionalFields",
          "display_name": "Additional Fields",
          "type": "COLLECTION",
          "default": "{",
          "description": "The release name",
          "display_options": {
            "show": {
              "operation": [
                "update"
              ]
            }
          }
        },
        {
          "name": "name",
          "display_name": "Name",
          "type": "STRING",
          "default": "",
          "description": "The release name"
        },
        {
          "name": "description",
          "display_name": "Description",
          "type": "STRING",
          "default": "",
          "description": "The description of the release. You can use Markdown."
        },
        {
          "name": "milestones",
          "display_name": "Milestones",
          "type": "STRING",
          "default": "",
          "description": "The title of each milestone to associate with the release (provide a titles list spearated with comma)"
        },
        {
          "name": "released_at",
          "display_name": "Released At",
          "type": "DATETIME",
          "default": "",
          "description": "The date when the release is/was ready"
        },
        {
          "name": "getRepositoryIssuesFilters",
          "display_name": "Filters",
          "type": "COLLECTION",
          "default": "{",
          "description": "Return only issues which are assigned to a specific user",
          "display_options": {
            "show": {
              "operation": [
                "getIssues"
              ]
            }
          }
        },
        {
          "name": "assignee_username",
          "display_name": "Assignee",
          "type": "STRING",
          "default": "",
          "description": "Return only issues which are assigned to a specific user"
        },
        {
          "name": "author_username",
          "display_name": "Creator",
          "type": "STRING",
          "default": "",
          "description": "Return only issues which were created by a specific user"
        },
        {
          "name": "search",
          "display_name": "Search",
          "type": "STRING",
          "default": "",
          "description": "Search issues against their title and description"
        },
        {
          "name": "labels",
          "display_name": "Labels",
          "type": "STRING",
          "default": "",
          "description": "Return only issues with the given labels. Multiple lables can be separated by comma."
        },
        {
          "name": "updated_after",
          "display_name": "Updated After",
          "type": "DATETIME",
          "default": "",
          "description": "Return only issues updated at or after this time"
        },
        {
          "name": "state",
          "display_name": "State",
          "type": "OPTIONS",
          "default": "opened",
          "description": "Returns issues with any state",
          "options": [
            {
              "name": "All",
              "value": "closed"
            },
            {
              "name": "Open",
              "value": "opened"
            }
          ]
        },
        {
          "name": "Closed",
          "display_name": "All",
          "type": "OPTIONS",
          "description": "Returns issues with any state"
        },
        {
          "name": "Updated At",
          "display_name": "Created At",
          "type": "OPTIONS",
          "description": "Sort by created date"
        },
        {
          "name": "Descending",
          "display_name": "Ascending",
          "type": "STRING",
          "description": "Sort in ascending order"
        },
        {
          "name": "filePath",
          "display_name": "Path",
          "type": "STRING",
          "default": "",
          "description": "The path of the folder to list",
          "display_options": {
            "show": {
              "operation": [
                "list"
              ]
            }
          }
        },
        {
          "name": "page",
          "display_name": "Page",
          "type": "NUMBER",
          "default": 1,
          "description": "Page of results to display",
          "display_options": {
            "show": {
              "operation": [
                "list"
              ]
            }
          }
        },
        {
          "name": "additionalParameters",
          "display_name": "Additional Parameters",
          "type": "COLLECTION",
          "default": "{",
          "description": "Additional fields to add",
          "display_options": {
            "show": {
              "operation": [
                "list"
              ]
            }
          }
        },
        {
          "name": "ref",
          "display_name": "Reference",
          "type": "STRING",
          "default": "",
          "description": "The name of the commit/branch/tag. Default: the repository\u2019s default branch (usually main)."
        },
        {
          "name": "recursive",
          "display_name": "Recursive",
          "type": "BOOLEAN",
          "default": false,
          "description": "Whether or not to get a recursive file tree. Default is false."
        },
        {
          "name": "asBinaryProperty",
          "display_name": "As Binary Property",
          "type": "BOOLEAN",
          "default": true,
          "description": "Whether to set the data of the file as binary property instead of returning the raw API response",
          "display_options": {
            "show": {
              "operation": [
                "get"
              ]
            }
          }
        },
        {
          "name": "binaryPropertyName",
          "display_name": "Put Output File in Field",
          "type": "STRING",
          "default": "data",
          "required": true,
          "display_options": {
            "show": {
              "operation": [
                "get"
              ]
            }
          }
        },
        {
          "name": "additionalParameters",
          "display_name": "Additional Parameters",
          "type": "COLLECTION",
          "default": "{",
          "description": "Additional fields to add",
          "display_options": {
            "show": {
              "operation": [
                "get"
              ]
            }
          }
        },
        {
          "name": "reference",
          "display_name": "Reference",
          "type": "STRING",
          "default": "",
          "description": "The name of the commit/branch/tag. Default: the repository\u2019s default branch (usually main)."
        },
        {
          "name": "binaryData",
          "display_name": "Binary File",
          "type": "BOOLEAN",
          "default": false,
          "required": true,
          "description": "Whether the data to upload should be taken from binary field",
          "display_options": {
            "show": {
              "operation": [
                "create",
                "edit"
              ]
            }
          }
        },
        {
          "name": "fileContent",
          "display_name": "File Content",
          "type": "STRING",
          "default": "",
          "required": true,
          "description": "The text content of the file",
          "display_options": {
            "show": {
              "operation": [
                "create",
                "edit"
              ]
            }
          }
        },
        {
          "name": "binaryPropertyName",
          "display_name": "Input Binary Field",
          "type": "STRING",
          "default": "data",
          "required": true,
          "display_options": {
            "show": {
              "operation": [
                "create",
                "edit"
              ]
            }
          }
        },
        {
          "name": "commitMessage",
          "display_name": "Commit Message",
          "type": "STRING",
          "default": "",
          "required": true,
          "display_options": {
            "show": {
              "operation": [
                "create",
                "delete",
                "edit"
              ]
            }
          }
        },
        {
          "name": "branch",
          "display_name": "Branch",
          "type": "STRING",
          "default": "",
          "required": true,
          "description": "Name of the new branch to create. The commit is added to this branch.",
          "display_options": {
            "show": {
              "operation": [
                "create",
                "delete",
                "edit"
              ]
            }
          }
        },
        {
          "name": "additionalParameters",
          "display_name": "Additional Parameters",
          "type": "COLLECTION",
          "default": "{",
          "description": "Additional fields to add",
          "display_options": {
            "show": {
              "operation": [
                "create",
                "delete",
                "edit"
              ]
            }
          }
        },
        {
          "name": "branchStart",
          "display_name": "Start Branch",
          "type": "STRING",
          "default": "",
          "description": "Name of the base branch to create the new branch from"
        },
        {
          "name": "name",
          "display_name": "author",
          "type": "STRING",
          "default": "",
          "description": "The name of the author of the commit"
        },
        {
          "name": "email",
          "display_name": "Email",
          "type": "STRING",
          "default": "",
          "description": "The email of the author of the commit"
        },
        {
          "name": "encoding",
          "display_name": "encoding",
          "type": "STRING",
          "default": "text",
          "description": "Change encoding to base64. Default is text."
        },
        {
          "name": "repository",
          "display_name": "Repository Name",
          "type": "STRING",
          "default": "",
          "required": true,
          "description": "The name of the repository"
        },
        {
          "name": "events",
          "display_name": "Events",
          "type": "MULTIOPTIONS",
          "default": "[]",
          "required": true,
          "description": "Any time any event is triggered (Wildcard Event)",
          "options": [
            {
              "name": "*",
              "value": "*"
            }
          ]
        }
      ]
    },
    "operations": [
      {
        "name": "create",
        "display_name": "Create",
        "description": "Create issue",
        "resource": "issue",
        "display_options": {
          "show": {
            "resource": [
              "issue"
            ]
          }
        }
      },
      {
        "name": "delete",
        "display_name": "Delete",
        "description": "Delete issue",
        "resource": "issue",
        "display_options": {
          "show": {
            "resource": [
              "issue"
            ]
          }
        }
      },
      {
        "name": "get",
        "display_name": "Get",
        "description": "Get issue",
        "resource": "issue",
        "display_options": {
          "show": {
            "resource": [
              "issue"
            ]
          }
        }
      },
      {
        "name": "getAll",
        "display_name": "Get Many",
        "description": "Get many issues",
        "resource": "issue",
        "display_options": {
          "show": {
            "resource": [
              "issue"
            ]
          }
        }
      },
      {
        "name": "update",
        "display_name": "Update",
        "description": "Update issue",
        "resource": "issue",
        "display_options": {
          "show": {
            "resource": [
              "issue"
            ]
          }
        }
      },
      {
        "name": "create",
        "display_name": "Create",
        "description": "Create repository",
        "resource": "repository",
        "display_options": {
          "show": {
            "resource": [
              "repository"
            ]
          }
        }
      },
      {
        "name": "delete",
        "display_name": "Delete",
        "description": "Delete repository",
        "resource": "repository",
        "display_options": {
          "show": {
            "resource": [
              "repository"
            ]
          }
        }
      },
      {
        "name": "get",
        "display_name": "Get",
        "description": "Get repository",
        "resource": "repository",
        "display_options": {
          "show": {
            "resource": [
              "repository"
            ]
          }
        }
      },
      {
        "name": "getAll",
        "display_name": "Get Many",
        "description": "Get many repositorys",
        "resource": "repository",
        "display_options": {
          "show": {
            "resource": [
              "repository"
            ]
          }
        }
      },
      {
        "name": "update",
        "display_name": "Update",
        "description": "Update repository",
        "resource": "repository",
        "display_options": {
          "show": {
            "resource": [
              "repository"
            ]
          }
        }
      },
      {
        "name": "create",
        "display_name": "Create",
        "description": "Create user",
        "resource": "user",
        "display_options": {
          "show": {
            "resource": [
              "user"
            ]
          }
        }
      },
      {
        "name": "delete",
        "display_name": "Delete",
        "description": "Delete user",
        "resource": "user",
        "display_options": {
          "show": {
            "resource": [
              "user"
            ]
          }
        }
      },
      {
        "name": "get",
        "display_name": "Get",
        "description": "Get user",
        "resource": "user",
        "display_options": {
          "show": {
            "resource": [
              "user"
            ]
          }
        }
      },
      {
        "name": "getAll",
        "display_name": "Get Many",
        "description": "Get many users",
        "resource": "user",
        "display_options": {
          "show": {
            "resource": [
              "user"
            ]
          }
        }
      },
      {
        "name": "update",
        "display_name": "Update",
        "description": "Update user",
        "resource": "user",
        "display_options": {
          "show": {
            "resource": [
              "user"
            ]
          }
        }
      },
      {
        "name": "create",
        "display_name": "Create",
        "description": "Create release",
        "resource": "release",
        "display_options": {
          "show": {
            "resource": [
              "release"
            ]
          }
        }
      },
      {
        "name": "delete",
        "display_name": "Delete",
        "description": "Delete release",
        "resource": "release",
        "display_options": {
          "show": {
            "resource": [
              "release"
            ]
          }
        }
      },
      {
        "name": "get",
        "display_name": "Get",
        "description": "Get release",
        "resource": "release",
        "display_options": {
          "show": {
            "resource": [
              "release"
            ]
          }
        }
      },
      {
        "name": "getAll",
        "display_name": "Get Many",
        "description": "Get many releases",
        "resource": "release",
        "display_options": {
          "show": {
            "resource": [
              "release"
            ]
          }
        }
      },
      {
        "name": "update",
        "display_name": "Update",
        "description": "Update release",
        "resource": "release",
        "display_options": {
          "show": {
            "resource": [
              "release"
            ]
          }
        }
      },
      {
        "name": "create",
        "display_name": "Create",
        "description": "Create file",
        "resource": "file",
        "display_options": {
          "show": {
            "resource": [
              "file"
            ]
          }
        }
      },
      {
        "name": "delete",
        "display_name": "Delete",
        "description": "Delete file",
        "resource": "file",
        "display_options": {
          "show": {
            "resource": [
              "file"
            ]
          }
        }
      },
      {
        "name": "get",
        "display_name": "Get",
        "description": "Get file",
        "resource": "file",
        "display_options": {
          "show": {
            "resource": [
              "file"
            ]
          }
        }
      },
      {
        "name": "getAll",
        "display_name": "Get Many",
        "description": "Get many files",
        "resource": "file",
        "display_options": {
          "show": {
            "resource": [
              "file"
            ]
          }
        }
      },
      {
        "name": "update",
        "display_name": "Update",
        "description": "Update file",
        "resource": "file",
        "display_options": {
          "show": {
            "resource": [
              "file"
            ]
          }
        }
      }
    ],
    "credentials": [
      {
        "name": "gitlabApi",
        "required": true,
        "display_options": {
          "show": {
            "authentication": [
              "gitlabApi"
            ]
          }
        }
      },
      {
        "name": "gitlabOAuth2Api",
        "required": true,
        "display_options": {
          "show": {
            "authentication": [
              "gitlabOAuth2Api"
            ]
          }
        }
      }
    ]
  },
  "trace_map": {
    "correlation_id": "gitlab-final-test-001",
    "node_type": "Gitlab",
    "trace_entries": [
      {
        "field_path": "operations[0]",
        "source": "ASSUMPTION",
        "evidence": "Standard operation 'create' assumed for resource 'issue'",
        "confidence": "medium",
        "assumption_rationale": "Standard CRUD operations for n8n resource"
      },
      {
        "field_path": "operations[1]",
        "source": "ASSUMPTION",
        "evidence": "Standard operation 'delete' assumed for resource 'issue'",
        "confidence": "medium",
        "assumption_rationale": "Standard CRUD operations for n8n resource"
      },
      {
        "field_path": "operations[2]",
        "source": "ASSUMPTION",
        "evidence": "Standard operation 'get' assumed for resource 'issue'",
        "confidence": "medium",
        "assumption_rationale": "Standard CRUD operations for n8n resource"
      },
      {
        "field_path": "operations[3]",
        "source": "ASSUMPTION",
        "evidence": "Standard operation 'getAll' assumed for resource 'issue'",
        "confidence": "medium",
        "assumption_rationale": "Standard CRUD operations for n8n resource"
      },
      {
        "field_path": "operations[4]",
        "source": "ASSUMPTION",
        "evidence": "Standard operation 'update' assumed for resource 'issue'",
        "confidence": "medium",
        "assumption_rationale": "Standard CRUD operations for n8n resource"
      },
      {
        "field_path": "operations[5]",
        "source": "ASSUMPTION",
        "evidence": "Standard operation 'create' assumed for resource 'repository'",
        "confidence": "medium",
        "assumption_rationale": "Standard CRUD operations for n8n resource"
      },
      {
        "field_path": "operations[6]",
        "source": "ASSUMPTION",
        "evidence": "Standard operation 'delete' assumed for resource 'repository'",
        "confidence": "medium",
        "assumption_rationale": "Standard CRUD operations for n8n resource"
      },
      {
        "field_path": "operations[7]",
        "source": "ASSUMPTION",
        "evidence": "Standard operation 'get' assumed for resource 'repository'",
        "confidence": "medium",
        "assumption_rationale": "Standard CRUD operations for n8n resource"
      },
      {
        "field_path": "operations[8]",
        "source": "ASSUMPTION",
        "evidence": "Standard operation 'getAll' assumed for resource 'repository'",
        "confidence": "medium",
        "assumption_rationale": "Standard CRUD operations for n8n resource"
      },
      {
        "field_path": "operations[9]",
        "source": "ASSUMPTION",
        "evidence": "Standard operation 'update' assumed for resource 'repository'",
        "confidence": "medium",
        "assumption_rationale": "Standard CRUD operations for n8n resource"
      },
      {
        "field_path": "operations[10]",
        "source": "ASSUMPTION",
        "evidence": "Standard operation 'create' assumed for resource 'user'",
        "confidence": "medium",
        "assumption_rationale": "Standard CRUD operations for n8n resource"
      },
      {
        "field_path": "operations[11]",
        "source": "ASSUMPTION",
        "evidence": "Standard operation 'delete' assumed for resource 'user'",
        "confidence": "medium",
        "assumption_rationale": "Standard CRUD operations for n8n resource"
      },
      {
        "field_path": "operations[12]",
        "source": "ASSUMPTION",
        "evidence": "Standard operation 'get' assumed for resource 'user'",
        "confidence": "medium",
        "assumption_rationale": "Standard CRUD operations for n8n resource"
      },
      {
        "field_path": "operations[13]",
        "source": "ASSUMPTION",
        "evidence": "Standard operation 'getAll' assumed for resource 'user'",
        "confidence": "medium",
        "assumption_rationale": "Standard CRUD operations for n8n resource"
      },
      {
        "field_path": "operations[14]",
        "source": "ASSUMPTION",
        "evidence": "Standard operation 'update' assumed for resource 'user'",
        "confidence": "medium",
        "assumption_rationale": "Standard CRUD operations for n8n resource"
      },
      {
        "field_path": "operations[15]",
        "source": "ASSUMPTION",
        "evidence": "Standard operation 'create' assumed for resource 'release'",
        "confidence": "medium",
        "assumption_rationale": "Standard CRUD operations for n8n resource"
      },
      {
        "field_path": "operations[16]",
        "source": "ASSUMPTION",
        "evidence": "Standard operation 'delete' assumed for resource 'release'",
        "confidence": "medium",
        "assumption_rationale": "Standard CRUD operations for n8n resource"
      },
      {
        "field_path": "operations[17]",
        "source": "ASSUMPTION",
        "evidence": "Standard operation 'get' assumed for resource 'release'",
        "confidence": "medium",
        "assumption_rationale": "Standard CRUD operations for n8n resource"
      },
      {
        "field_path": "operations[18]",
        "source": "ASSUMPTION",
        "evidence": "Standard operation 'getAll' assumed for resource 'release'",
        "confidence": "medium",
        "assumption_rationale": "Standard CRUD operations for n8n resource"
      },
      {
        "field_path": "operations[19]",
        "source": "ASSUMPTION",
        "evidence": "Standard operation 'update' assumed for resource 'release'",
        "confidence": "medium",
        "assumption_rationale": "Standard CRUD operations for n8n resource"
      },
      {
        "field_path": "operations[20]",
        "source": "ASSUMPTION",
        "evidence": "Standard operation 'create' assumed for resource 'file'",
        "confidence": "medium",
        "assumption_rationale": "Standard CRUD operations for n8n resource"
      },
      {
        "field_path": "operations[21]",
        "source": "ASSUMPTION",
        "evidence": "Standard operation 'delete' assumed for resource 'file'",
        "confidence": "medium",
        "assumption_rationale": "Standard CRUD operations for n8n resource"
      },
      {
        "field_path": "operations[22]",
        "source": "ASSUMPTION",
        "evidence": "Standard operation 'get' assumed for resource 'file'",
        "confidence": "medium",
        "assumption_rationale": "Standard CRUD operations for n8n resource"
      },
      {
        "field_path": "operations[23]",
        "source": "ASSUMPTION",
        "evidence": "Standard operation 'getAll' assumed for resource 'file'",
        "confidence": "medium",
        "assumption_rationale": "Standard CRUD operations for n8n resource"
      },
      {
        "field_path": "operations[24]",
        "source": "ASSUMPTION",
        "evidence": "Standard operation 'update' assumed for resource 'file'",
        "confidence": "medium",
        "assumption_rationale": "Standard CRUD operations for n8n resource"
      },
      {
        "field_path": "credentials[0]",
        "source": "SOURCE_CODE",
        "evidence": "Credential 'gitlabApi' extracted from source",
        "confidence": "high"
      },
      {
        "field_path": "credentials[1]",
        "source": "SOURCE_CODE",
        "evidence": "Credential 'gitlabOAuth2Api' extracted from source",
        "confidence": "high"
      }
    ],
    "generated_at": "2026-02-02T14:49:01.030205",
    "skill_version": "1.0.0",
    "_hybrid_metadata": {
      "source_type": "TYPE1",
      "extraction_confidence": 0.6,
      "advisor_used": false,
      "assumption_ratio": 0.9259259259259259,
      "deterministic_operations": 2,
      "assumption_operations": 25
    }
  },
  "tests_passed": false,
  "validation_passed": true,
  "fix_iterations": 0,
  "source_files": [],
  "source_hash": null
}